[{
  "_id": {
    "$oid": "61a690f1a7f2d302ad5606a0"
  },
  "key": 1,
  "id": {
    "$oid": "61a68f4dfc13ae699b00020d"
  },
  "GPS": {
    "latitude": 39.9048438,
    "longitude": 117.2490532
  },
  "city": "Youguzhuang",
  "name": "COVID CENTER 21",
  "type": "specialized center",
  "address": "8 Sunnyside Junction"
},{
  "_id": {
    "$oid": "61a690f1a7f2d302ad5606a1"
  },
  "key": 2,
  "id": {
    "$oid": "61a68f4dfc13ae699b00020e"
  },
  "GPS": {
    "latitude": -21.7034017,
    "longitude": -47.27079
  },
  "city": "Tambaú",
  "name": "Norton Sound Regional Hospital",
  "type": "hospital",
  "address": "20229 Bellgrove Plaza",
  "department": 8
},{
  "_id": {
    "$oid": "61a690f1a7f2d302ad5606a2"
  },
  "key": 3,
  "id": {
    "$oid": "61a68f4dfc13ae699b00020f"
  },
  "GPS": {
    "latitude": 53.09697,
    "longitude": -113.4729375
  },
  "city": "Millet",
  "name": "Pacific Pharmacy Pte Ltd",
  "type": "pharmacy",
  "address": "3 Spenser Avenue"
},{
  "_id": {
    "$oid": "61a690f1a7f2d302ad5606a3"
  },
  "key": 4,
  "id": {
    "$oid": "61a68f4dfc13ae699b000210"
  },
  "GPS": {
    "latitude": 26.641315,
    "longitude": 100.222545
  },
  "city": "Baisha",
  "name": "Pharmacy@IB CGH (The Integrated Building)",
  "type": "pharmacy",
  "address": "5 Rowland Alley"
},{
  "_id": {
    "$oid": "61a690f1a7f2d302ad5606a4"
  },
  "key": 5,
  "id": {
    "$oid": "61a68f4dfc13ae699b000211"
  },
  "GPS": {
    "latitude": 25.0676256,
    "longitude": 34.8789697
  },
  "city": "Marsa Alam",
  "name": "Wiregrass Medical Center",
  "type": "hospital",
  "address": "5578 6th Street",
  "department": 4
},{
  "_id": {
    "$oid": "61a690f1a7f2d302ad5606a5"
  },
  "key": 6,
  "id": {
    "$oid": "61a68f4dfc13ae699b000212"
  },
  "GPS": {
    "latitude": 19.3947363,
    "longitude": -70.5263459
  },
  "city": "Salcedo",
  "name": "COVID CENTER 14",
  "type": "specialized center",
  "address": "34 Blaine Point"
},{
  "_id": {
    "$oid": "61a690f1a7f2d302ad5606a6"
  },
  "key": 7,
  "id": {
    "$oid": "61a68f4dfc13ae699b000213"
  },
  "GPS": {
    "latitude": 7.834501,
    "longitude": 124.106681
  },
  "city": "Madamba",
  "name": "COVID CENTER 26",
  "type": "specialized center",
  "address": "68045 Bonner Trail"
},{
  "_id": {
    "$oid": "61a690f1a7f2d302ad5606a7"
  },
  "key": 8,
  "id": {
    "$oid": "61a68f4dfc13ae699b000214"
  },
  "GPS": {
    "latitude": -6.1418556,
    "longitude": 106.8281623
  },
  "city": "Mangga Dua",
  "name": "Lawrence Medical Center",
  "type": "hospital",
  "address": "54040 Fairfield Trail",
  "department": 9
},{
  "_id": {
    "$oid": "61a690f1a7f2d302ad5606a8"
  },
  "key": 9,
  "id": {
    "$oid": "61a68f4dfc13ae699b000215"
  },
  "GPS": {
    "latitude": -7.4111208,
    "longitude": 108.1221146
  },
  "city": "Sukasenang",
  "name": "D C H Regional Medical Center",
  "type": "hospital",
  "address": "4859 Packers Hill",
  "department": 4
},{
  "_id": {
    "$oid": "61a690f1a7f2d302ad5606a9"
  },
  "key": 10,
  "id": {
    "$oid": "61a68f4dfc13ae699b000216"
  },
  "GPS": {
    "latitude": 56.0764877,
    "longitude": 38.5052448
  },
  "city": "Noginsk-9",
  "name": "COVID CENTER 3",
  "type": "specialized center",
  "address": "04 John Wall Way"
},{
  "_id": {
    "$oid": "61a690f1a7f2d302ad5606aa"
  },
  "key": 11,
  "id": {
    "$oid": "61a68f4dfc13ae699b000217"
  },
  "GPS": {
    "latitude": -18.4943258,
    "longitude": -40.4657826
  },
  "city": "Nova Venécia",
  "name": "University Of Alabama Hospital",
  "type": "hospital",
  "address": "60 Atwood Parkway",
  "department": 8
},{
  "_id": {
    "$oid": "61a690f1a7f2d302ad5606ab"
  },
  "key": 12,
  "id": {
    "$oid": "61a68f4dfc13ae699b000218"
  },
  "GPS": {
    "latitude": 48.3667546,
    "longitude": 25.2298685
  },
  "city": "Rozhniv",
  "name": "Rmc Jacksonville",
  "type": "hospital",
  "address": "69353 Dwight Plaza",
  "department": 5
},{
  "_id": {
    "$oid": "61a690f1a7f2d302ad5606ac"
  },
  "key": 13,
  "id": {
    "$oid": "61a68f4dfc13ae699b000219"
  },
  "GPS": {
    "latitude": 15.6594009,
    "longitude": 120.5306172
  },
  "city": "Capulaan",
  "name": "NATIONAL CANCER CENTRE PHARMACY (LEVEL 1)",
  "type": "pharmacy",
  "address": "3 Mariners Cove Center"
},{
  "_id": {
    "$oid": "61a690f1a7f2d302ad5606ad"
  },
  "key": 14,
  "id": {
    "$oid": "61a68f4dfc13ae699b00021a"
  },
  "GPS": {
    "latitude": -12.930823,
    "longitude": -75.7803892
  },
  "city": "Viñac",
  "name": "St Vincents Blount",
  "type": "hospital",
  "address": "4 Thompson Plaza",
  "department": 7
},{
  "_id": {
    "$oid": "61a690f1a7f2d302ad5606ae"
  },
  "key": 15,
  "id": {
    "$oid": "61a68f4dfc13ae699b00021b"
  },
  "GPS": {
    "latitude": 41.0489611,
    "longitude": -8.5265537
  },
  "city": "São Miguel",
  "name": "National Centre for Infectious Disease (Outpatient Pharmacy)",
  "type": "pharmacy",
  "address": "20135 Dunning Trail"
},{
  "_id": {
    "$oid": "61a690f1a7f2d302ad5606af"
  },
  "key": 16,
  "id": {
    "$oid": "61a68f4dfc13ae699b00021c"
  },
  "GPS": {
    "latitude": 11.8759644,
    "longitude": -86.0504111
  },
  "city": "Diriomo",
  "name": "MEDI-LINK PHARMACY",
  "type": "pharmacy",
  "address": "0 Thackeray Hill"
},{
  "_id": {
    "$oid": "61a690f1a7f2d302ad5606b0"
  },
  "key": 17,
  "id": {
    "$oid": "61a68f4dfc13ae699b00021d"
  },
  "GPS": {
    "latitude": -9.8610821,
    "longitude": 124.4697283
  },
  "city": "Noebesa",
  "name": "Petersburg Medical Center",
  "type": "hospital",
  "address": "7966 Loeprich Plaza",
  "department": 10
},{
  "_id": {
    "$oid": "61a690f1a7f2d302ad5606b1"
  },
  "key": 18,
  "id": {
    "$oid": "61a68f4dfc13ae699b00021e"
  },
  "GPS": {
    "latitude": 58.5560583,
    "longitude": 26.6261976
  },
  "city": "Tabivere",
  "name": "Haematology Pharmacy (Block 7)",
  "type": "pharmacy",
  "address": "5 Huxley Park"
},{
  "_id": {
    "$oid": "61a690f1a7f2d302ad5606b2"
  },
  "key": 19,
  "id": {
    "$oid": "61a68f4dfc13ae699b00021f"
  },
  "GPS": {
    "latitude": 23.913205,
    "longitude": 116.464983
  },
  "city": "Liuhuang",
  "name": "Alaska Regional Hospital",
  "type": "hospital",
  "address": "2 Haas Drive",
  "department": 1
},{
  "_id": {
    "$oid": "61a690f1a7f2d302ad5606b3"
  },
  "key": 20,
  "id": {
    "$oid": "61a68f4dfc13ae699b000220"
  },
  "GPS": {
    "latitude": 7.55,
    "longitude": 3.43333
  },
  "city": "Orita Eruwa",
  "name": "Highlands Medical Center",
  "type": "hospital",
  "address": "7500 Stang Parkway",
  "department": 4
},{
  "_id": {
    "$oid": "61a690f1a7f2d302ad5606b4"
  },
  "key": 21,
  "id": {
    "$oid": "61a68f4dfc13ae699b000221"
  },
  "GPS": {
    "latitude": 40.076762,
    "longitude": 113.300129
  },
  "city": "Ditang",
  "name": "Providence Alaska Medical Center",
  "type": "hospital",
  "address": "7 Morning Parkway",
  "department": 3
},{
  "_id": {
    "$oid": "61a690f1a7f2d302ad5606b5"
  },
  "key": 22,
  "id": {
    "$oid": "61a68f4dfc13ae699b000222"
  },
  "GPS": {
    "latitude": -32.4499018,
    "longitude": -71.2325958
  },
  "city": "La Ligua",
  "name": "CGH Pharmacy B",
  "type": "pharmacy",
  "address": "87944 Algoma Alley"
},{
  "_id": {
    "$oid": "61a690f1a7f2d302ad5606b6"
  },
  "key": 23,
  "id": {
    "$oid": "61a68f4dfc13ae699b000223"
  },
  "GPS": {
    "latitude": 31.6095648,
    "longitude": 64.4082082
  },
  "city": "Lashkar Gāh",
  "name": "COVID CENTER 47",
  "type": "specialized center",
  "address": "2305 Scott Junction"
},{
  "_id": {
    "$oid": "61a690f1a7f2d302ad5606b7"
  },
  "key": 24,
  "id": {
    "$oid": "61a68f4dfc13ae699b000224"
  },
  "GPS": {
    "latitude": 47.5015067,
    "longitude": 34.6341859
  },
  "city": "Energodar",
  "name": "Kingman Regional Medical Center",
  "type": "hospital",
  "address": "013 Eliot Alley",
  "department": 4
},{
  "_id": {
    "$oid": "61a690f1a7f2d302ad5606b8"
  },
  "key": 25,
  "id": {
    "$oid": "61a68f4dfc13ae699b000225"
  },
  "GPS": {
    "latitude": 49.1931313,
    "longitude": -0.3907558
  },
  "city": "Caen",
  "name": "COVID CENTER 28",
  "type": "specialized center",
  "address": "73 Mariners Cove Street"
},{
  "_id": {
    "$oid": "61a690f1a7f2d302ad5606b9"
  },
  "key": 26,
  "id": {
    "$oid": "61a68f4dfc13ae699b000226"
  },
  "GPS": {
    "latitude": 31.4637723,
    "longitude": -100.4370375
  },
  "city": "San Angelo",
  "name": "Georgiana Medical Center",
  "type": "hospital",
  "address": "6 Waxwing Street",
  "department": 6
},{
  "_id": {
    "$oid": "61a690f1a7f2d302ad5606ba"
  },
  "key": 27,
  "id": {
    "$oid": "61a68f4dfc13ae699b000227"
  },
  "GPS": {
    "latitude": 48.6138851,
    "longitude": 14.2281446
  },
  "city": "Loučovice",
  "name": "National University Hospital (s) Pte Ltd (Pharmacy @ NCIS)",
  "type": "pharmacy",
  "address": "51805 Badeau Hill"
},{
  "_id": {
    "$oid": "61a690f1a7f2d302ad5606bb"
  },
  "key": 28,
  "id": {
    "$oid": "61a68f4dfc13ae699b000228"
  },
  "GPS": {
    "latitude": -28.5860306,
    "longitude": 30.8843434
  },
  "city": "Nkandla",
  "name": "Helen Keller Memorial Hospital",
  "type": "hospital",
  "address": "96 Kedzie Avenue",
  "department": 4
},{
  "_id": {
    "$oid": "61a690f1a7f2d302ad5606bc"
  },
  "key": 29,
  "id": {
    "$oid": "61a68f4dfc13ae699b000229"
  },
  "GPS": {
    "latitude": 53.69889,
    "longitude": 31.71417
  },
  "city": "Horad Krychaw",
  "name": "NATIONAL CANCER CENTRE PHARMACY (LEVEL 1)",
  "type": "pharmacy",
  "address": "90234 Bonner Hill"
},{
  "_id": {
    "$oid": "61a690f1a7f2d302ad5606bd"
  },
  "key": 30,
  "id": {
    "$oid": "61a68f4dfc13ae699b00022a"
  },
  "GPS": {
    "latitude": 2.9182648,
    "longitude": 101.6982899
  },
  "city": "Putrajaya",
  "name": "Marion Regional Medical Center",
  "type": "hospital",
  "address": "937 Melrose Drive",
  "department": 1
},{
  "_id": {
    "$oid": "61a690f1a7f2d302ad5606be"
  },
  "key": 31,
  "id": {
    "$oid": "61a68f4dfc13ae699b00022b"
  },
  "GPS": {
    "latitude": 9.090009,
    "longitude": 126.162783
  },
  "city": "Tandag",
  "name": "Highlands Medical Center",
  "type": "hospital",
  "address": "5842 Petterle Lane",
  "department": 7
},{
  "_id": {
    "$oid": "61a690f1a7f2d302ad5606bf"
  },
  "key": 32,
  "id": {
    "$oid": "61a68f4dfc13ae699b00022c"
  },
  "GPS": {
    "latitude": -24.8472072,
    "longitude": -56.3530514
  },
  "city": "Yataity del Norte",
  "name": "CELCODE DERMAL LAB PTE LTD",
  "type": "pharmacy",
  "address": "4 Lighthouse Bay Drive"
},{
  "_id": {
    "$oid": "61a690f1a7f2d302ad5606c0"
  },
  "key": 33,
  "id": {
    "$oid": "61a68f4dfc13ae699b00022d"
  },
  "GPS": {
    "latitude": 40.5045999,
    "longitude": -7.9318645
  },
  "city": "Póvoa de Santo António",
  "name": "Tanner Medical Center-east Alabama",
  "type": "hospital",
  "address": "9 Troy Lane",
  "department": 4
},{
  "_id": {
    "$oid": "61a690f1a7f2d302ad5606c1"
  },
  "key": 34,
  "id": {
    "$oid": "61a68f4dfc13ae699b00022e"
  },
  "GPS": {
    "latitude": -20.4670046,
    "longitude": -55.7872944
  },
  "city": "Aquidauana",
  "name": "COVID CENTER 19",
  "type": "specialized center",
  "address": "390 Schlimgen Park"
},{
  "_id": {
    "$oid": "61a690f1a7f2d302ad5606c2"
  },
  "key": 35,
  "id": {
    "$oid": "61a68f4dfc13ae699b00022f"
  },
  "GPS": {
    "latitude": 39.8007621,
    "longitude": 116.504048
  },
  "city": "Dabao",
  "name": "COVID CENTER 26",
  "type": "specialized center",
  "address": "718 Northfield Pass"
},{
  "_id": {
    "$oid": "61a690f1a7f2d302ad5606c3"
  },
  "key": 36,
  "id": {
    "$oid": "61a68f4dfc13ae699b000230"
  },
  "GPS": {
    "latitude": 15.1757062,
    "longitude": 120.5879653
  },
  "city": "Mabalacat",
  "name": "Baptist Medical Center South",
  "type": "hospital",
  "address": "0120 Donald Hill",
  "department": 6
},{
  "_id": {
    "$oid": "61a690f1a7f2d302ad5606c4"
  },
  "key": 37,
  "id": {
    "$oid": "61a68f4dfc13ae699b000231"
  },
  "GPS": {
    "latitude": 25.635605,
    "longitude": 102.57997
  },
  "city": "Dasongshu",
  "name": "WATSONS PERSONAL CARE STORES (TIONG BAHRU PLAZA)",
  "type": "pharmacy",
  "address": "4027 Spohn Drive"
},{
  "_id": {
    "$oid": "61a690f1a7f2d302ad5606c5"
  },
  "key": 38,
  "id": {
    "$oid": "61a68f4dfc13ae699b000232"
  },
  "GPS": {
    "latitude": 57.6680135,
    "longitude": 63.0632053
  },
  "city": "Irbit",
  "name": "Prattville Baptist Hospital",
  "type": "hospital",
  "address": "10565 Glendale Road",
  "department": 8
},{
  "_id": {
    "$oid": "61a690f1a7f2d302ad5606c6"
  },
  "key": 39,
  "id": {
    "$oid": "61a68f4dfc13ae699b000233"
  },
  "GPS": {
    "latitude": -10.0569,
    "longitude": 124.1295
  },
  "city": "Oehaunu",
  "name": "COVID CENTER 16",
  "type": "specialized center",
  "address": "163 Sycamore Circle"
},{
  "_id": {
    "$oid": "61a690f1a7f2d302ad5606c7"
  },
  "key": 40,
  "id": {
    "$oid": "61a68f4dfc13ae699b000234"
  },
  "GPS": {
    "latitude": -41.1751049,
    "longitude": 174.9385347
  },
  "city": "Invercargill",
  "name": "COVID CENTER 46",
  "type": "specialized center",
  "address": "49457 Center Road"
},{
  "_id": {
    "$oid": "61a690f1a7f2d302ad5606c8"
  },
  "key": 41,
  "id": {
    "$oid": "61a68f4dfc13ae699b000235"
  },
  "GPS": {
    "latitude": 8.0991923,
    "longitude": -10.6956979
  },
  "city": "Pendembu",
  "name": "Springhill Memorial Hospital",
  "type": "hospital",
  "address": "34921 Jenna Alley",
  "department": 7
},{
  "_id": {
    "$oid": "61a690f1a7f2d302ad5606c9"
  },
  "key": 42,
  "id": {
    "$oid": "61a68f4dfc13ae699b000236"
  },
  "GPS": {
    "latitude": -17.8938032,
    "longitude": -39.6930912
  },
  "city": "Nova Viçosa",
  "name": "Petersburg Medical Center",
  "type": "hospital",
  "address": "5506 Anzinger Hill",
  "department": 4
},{
  "_id": {
    "$oid": "61a690f1a7f2d302ad5606ca"
  },
  "key": 43,
  "id": {
    "$oid": "61a68f4dfc13ae699b000237"
  },
  "GPS": {
    "latitude": 30.741991,
    "longitude": 121.341969
  },
  "city": "Jinshan",
  "name": "COVID CENTER 41",
  "type": "specialized center",
  "address": "712 Brown Park"
},{
  "_id": {
    "$oid": "61a690f1a7f2d302ad5606cb"
  },
  "key": 44,
  "id": {
    "$oid": "61a68f4dfc13ae699b000238"
  },
  "GPS": {
    "latitude": 13.8151887,
    "longitude": 121.436308
  },
  "city": "Poctol",
  "name": "National Centre for Infectious Disease (Outpatient Pharmacy)",
  "type": "pharmacy",
  "address": "83468 Hollow Ridge Road"
},{
  "_id": {
    "$oid": "61a690f1a7f2d302ad5606cc"
  },
  "key": 45,
  "id": {
    "$oid": "61a68f4dfc13ae699b000239"
  },
  "GPS": {
    "latitude": 48.7790663,
    "longitude": 38.564841
  },
  "city": "Toshkivka",
  "name": "University Of South Alabama Medical Center",
  "type": "hospital",
  "address": "1 Melvin Crossing",
  "department": 6
},{
  "_id": {
    "$oid": "61a690f1a7f2d302ad5606cd"
  },
  "key": 46,
  "id": {
    "$oid": "61a68f4dfc13ae699b00023a"
  },
  "GPS": {
    "latitude": 9.128588,
    "longitude": 124.672209
  },
  "city": "Catarman",
  "name": "COVID CENTER 51",
  "type": "specialized center",
  "address": "64321 Commercial Crossing"
},{
  "_id": {
    "$oid": "61a690f1a7f2d302ad5606ce"
  },
  "key": 47,
  "id": {
    "$oid": "61a68f4dfc13ae699b00023b"
  },
  "GPS": {
    "latitude": 34.5646414,
    "longitude": 133.4167423
  },
  "city": "Kannabechō-yahiro",
  "name": "Jackson Medical Center",
  "type": "hospital",
  "address": "00783 Pawling Way",
  "department": 8
},{
  "_id": {
    "$oid": "61a690f1a7f2d302ad5606cf"
  },
  "key": 48,
  "id": {
    "$oid": "61a68f4dfc13ae699b00023c"
  },
  "GPS": {
    "latitude": 38.0772641,
    "longitude": 22.6326975
  },
  "city": "Xylókastro",
  "name": "Tan Tock Seng Hospital (Pharmacy Level 2)",
  "type": "pharmacy",
  "address": "3994 Reinke Way"
},{
  "_id": {
    "$oid": "61a690f1a7f2d302ad5606d0"
  },
  "key": 49,
  "id": {
    "$oid": "61a68f4dfc13ae699b00023d"
  },
  "GPS": {
    "latitude": 45.4885295,
    "longitude": 41.1600688
  },
  "city": "Novoaleksandrovsk",
  "name": "MOUNT ELIZABETH NOVENA HOSPITAL PHARMACY",
  "type": "pharmacy",
  "address": "85 Declaration Lane"
},{
  "_id": {
    "$oid": "61a690f1a7f2d302ad5606d1"
  },
  "key": 50,
  "id": {
    "$oid": "61a68f4dfc13ae699b00023e"
  },
  "GPS": {
    "latitude": 50.0804826,
    "longitude": 16.9364145
  },
  "city": "Hanušovice",
  "name": "Admiralty Medical Centre Pharmacy",
  "type": "pharmacy",
  "address": "9606 Schiller Point"
},{
  "_id": {
    "$oid": "61a690f1a7f2d302ad5606d2"
  },
  "key": 51,
  "id": {
    "$oid": "61a68f4dfc13ae699b00023f"
  },
  "GPS": {
    "latitude": 38.8162965,
    "longitude": 24.5955356
  },
  "city": "Skýros",
  "name": "Sengkang General Hospital Outpatient Pharmacy",
  "type": "pharmacy",
  "address": "98 Bunker Hill Terrace"
},{
  "_id": {
    "$oid": "61a690f1a7f2d302ad5606d3"
  },
  "key": 52,
  "id": {
    "$oid": "61a68f4dfc13ae699b000240"
  },
  "GPS": {
    "latitude": 41.4548181,
    "longitude": -8.2493359
  },
  "city": "Atães",
  "name": "Russell Medical Center",
  "type": "hospital",
  "address": "537 Vidon Alley",
  "department": 7
},{
  "_id": {
    "$oid": "61a690f1a7f2d302ad5606d4"
  },
  "key": 53,
  "id": {
    "$oid": "61a68f4dfc13ae699b000241"
  },
  "GPS": {
    "latitude": -8.2012757,
    "longitude": 112.1012912
  },
  "city": "Suruhwadang",
  "name": "COVID CENTER 32",
  "type": "specialized center",
  "address": "7557 Granby Parkway"
},{
  "_id": {
    "$oid": "61a690f1a7f2d302ad5606d5"
  },
  "key": 54,
  "id": {
    "$oid": "61a68f4dfc13ae699b000242"
  },
  "GPS": {
    "latitude": -6.8065,
    "longitude": 111.3806
  },
  "city": "Sulang Tengah",
  "name": "University Of S A Children's And Women's Hos",
  "type": "hospital",
  "address": "8652 Crownhardt Crossing",
  "department": 10
},{
  "_id": {
    "$oid": "61a690f1a7f2d302ad5606d6"
  },
  "key": 55,
  "id": {
    "$oid": "61a68f4dfc13ae699b000243"
  },
  "GPS": {
    "latitude": 30.1755285,
    "longitude": 121.3325306
  },
  "city": "Poxi",
  "name": "Russell Medical Center",
  "type": "hospital",
  "address": "969 Rigney Street",
  "department": 3
},{
  "_id": {
    "$oid": "61a690f1a7f2d302ad5606d7"
  },
  "key": 56,
  "id": {
    "$oid": "61a68f4dfc13ae699b000244"
  },
  "GPS": {
    "latitude": 37.7688197,
    "longitude": 140.7154397
  },
  "city": "Tamano",
  "name": "Choctaw General Hospital",
  "type": "hospital",
  "address": "9 Brentwood Hill",
  "department": 9
},{
  "_id": {
    "$oid": "61a690f1a7f2d302ad5606d8"
  },
  "key": 57,
  "id": {
    "$oid": "61a68f4dfc13ae699b000245"
  },
  "GPS": {
    "latitude": 41.2994958,
    "longitude": 69.2400734
  },
  "city": "Tashkent",
  "name": "St Joseph's Hospital",
  "type": "hospital",
  "address": "7346 Melby Lane",
  "department": 3
},{
  "_id": {
    "$oid": "61a690f1a7f2d302ad5606d9"
  },
  "key": 58,
  "id": {
    "$oid": "61a68f4dfc13ae699b000246"
  },
  "GPS": {
    "latitude": 49.7102798,
    "longitude": 20.9509659
  },
  "city": "Bobowa",
  "name": "The Japanese Association Clinic Singapore",
  "type": "pharmacy",
  "address": "58657 Brown Hill"
},{
  "_id": {
    "$oid": "61a690f1a7f2d302ad5606da"
  },
  "key": 59,
  "id": {
    "$oid": "61a68f4dfc13ae699b000247"
  },
  "GPS": {
    "latitude": 41.65041,
    "longitude": 59.9164
  },
  "city": "Tagta",
  "name": "GRACE HEALTHCARE",
  "type": "pharmacy",
  "address": "357 Kipling Plaza"
},{
  "_id": {
    "$oid": "61a690f1a7f2d302ad5606db"
  },
  "key": 60,
  "id": {
    "$oid": "61a68f4dfc13ae699b000248"
  },
  "GPS": {
    "latitude": 12.7871909,
    "longitude": 44.9836775
  },
  "city": "At Tawāhī",
  "name": "Abrazo Central Campus",
  "type": "hospital",
  "address": "244 Sunbrook Hill",
  "department": 1
},{
  "_id": {
    "$oid": "61a690f1a7f2d302ad5606dc"
  },
  "key": 61,
  "id": {
    "$oid": "61a68f4dfc13ae699b000249"
  },
  "GPS": {
    "latitude": 43.8273805,
    "longitude": 1.3951553
  },
  "city": "Toulouse",
  "name": "WOODS PHARMACY PTE LTD",
  "type": "pharmacy",
  "address": "4313 Oneill Drive"
},{
  "_id": {
    "$oid": "61a690f1a7f2d302ad5606dd"
  },
  "key": 62,
  "id": {
    "$oid": "61a68f4dfc13ae699b00024a"
  },
  "GPS": {
    "latitude": 52.2828507,
    "longitude": 16.8550365
  },
  "city": "Puszczykowo",
  "name": "Medical West",
  "type": "hospital",
  "address": "11 Forster Hill",
  "department": 4
},{
  "_id": {
    "$oid": "61a690f1a7f2d302ad5606de"
  },
  "key": 63,
  "id": {
    "$oid": "61a68f4dfc13ae699b00024b"
  },
  "GPS": {
    "latitude": 41.4493594,
    "longitude": 44.5488663
  },
  "city": "Bolnisi",
  "name": "Manapharma Pharmacy",
  "type": "pharmacy",
  "address": "64961 Rusk Hill"
},{
  "_id": {
    "$oid": "61a690f1a7f2d302ad5606df"
  },
  "key": 64,
  "id": {
    "$oid": "61a68f4dfc13ae699b00024c"
  },
  "GPS": {
    "latitude": -11.8532073,
    "longitude": -75.508016
  },
  "city": "Paccha",
  "name": "Northeast Alabama Regional Medical Center",
  "type": "hospital",
  "address": "397 Huxley Circle",
  "department": 3
},{
  "_id": {
    "$oid": "61a690f1a7f2d302ad5606e0"
  },
  "key": 65,
  "id": {
    "$oid": "61a68f4dfc13ae699b00024d"
  },
  "GPS": {
    "latitude": -4.5702358,
    "longitude": 30.1011836
  },
  "city": "Kasulu",
  "name": "Citizens Baptist Medical Center",
  "type": "hospital",
  "address": "6954 Sunbrook Terrace",
  "department": 6
},{
  "_id": {
    "$oid": "61a690f1a7f2d302ad5606e1"
  },
  "key": 66,
  "id": {
    "$oid": "61a68f4dfc13ae699b00024e"
  },
  "GPS": {
    "latitude": 53.3788422,
    "longitude": -1.4730092
  },
  "city": "Sheffield",
  "name": "Scottsdale Osborn Medical Center",
  "type": "hospital",
  "address": "354 Sommers Trail",
  "department": 5
},{
  "_id": {
    "$oid": "61a690f1a7f2d302ad5606e2"
  },
  "key": 67,
  "id": {
    "$oid": "61a68f4dfc13ae699b00024f"
  },
  "GPS": {
    "latitude": 66.2185015,
    "longitude": 23.0524409
  },
  "city": "Överkalix",
  "name": "P & L Pharmacy Pte Ltd",
  "type": "pharmacy",
  "address": "3802 Rusk Plaza"
},{
  "_id": {
    "$oid": "61a690f1a7f2d302ad5606e3"
  },
  "key": 68,
  "id": {
    "$oid": "61a68f4dfc13ae699b000250"
  },
  "GPS": {
    "latitude": 13.78024,
    "longitude": 43.86901
  },
  "city": "Ar Rubū‘",
  "name": "St Vincent's Chilton",
  "type": "hospital",
  "address": "533 Little Fleur Crossing",
  "department": 5
},{
  "_id": {
    "$oid": "61a690f1a7f2d302ad5606e4"
  },
  "key": 69,
  "id": {
    "$oid": "61a68f4dfc13ae699b000251"
  },
  "GPS": {
    "latitude": 37.54,
    "longitude": -77.45
  },
  "city": "Richmond",
  "name": "South Peninsula Hospital",
  "type": "hospital",
  "address": "427 Harbort Court",
  "department": 9
},{
  "_id": {
    "$oid": "61a690f1a7f2d302ad5606e5"
  },
  "key": 70,
  "id": {
    "$oid": "61a68f4dfc13ae699b000252"
  },
  "GPS": {
    "latitude": 27.519549,
    "longitude": 114.073416
  },
  "city": "Xinquan",
  "name": "Medical Center Enterprise",
  "type": "hospital",
  "address": "4 Kennedy Court",
  "department": 7
},{
  "_id": {
    "$oid": "61a690f1a7f2d302ad5606e6"
  },
  "key": 71,
  "id": {
    "$oid": "61a68f4dfc13ae699b000253"
  },
  "GPS": {
    "latitude": 2.7697259,
    "longitude": -60.7126625
  },
  "city": "Boa Vista",
  "name": "Floyd Cherokee Medical Center",
  "type": "hospital",
  "address": "137 Jackson Plaza",
  "department": 2
},{
  "_id": {
    "$oid": "61a690f1a7f2d302ad5606e7"
  },
  "key": 72,
  "id": {
    "$oid": "61a68f4dfc13ae699b000254"
  },
  "GPS": {
    "latitude": 11.2755407,
    "longitude": 49.1878994
  },
  "city": "Bosaso",
  "name": "COVID CENTER 26",
  "type": "specialized center",
  "address": "45691 Forster Alley"
},{
  "_id": {
    "$oid": "61a690f1a7f2d302ad5606e8"
  },
  "key": 73,
  "id": {
    "$oid": "61a68f4dfc13ae699b000255"
  },
  "GPS": {
    "latitude": 44.439233,
    "longitude": 129.500041
  },
  "city": "Wenchun",
  "name": "Specialist Compounding Pharmacy Pte Ltd",
  "type": "pharmacy",
  "address": "50393 Bultman Trail"
},{
  "_id": {
    "$oid": "61a690f1a7f2d302ad5606e9"
  },
  "key": 74,
  "id": {
    "$oid": "61a68f4dfc13ae699b000256"
  },
  "GPS": {
    "latitude": 24.9936281,
    "longitude": 121.3009798
  },
  "city": "Taoyuan",
  "name": "GRACE HEALTHCARE",
  "type": "pharmacy",
  "address": "2 Pepper Wood Plaza"
},{
  "_id": {
    "$oid": "61a690f1a7f2d302ad5606ea"
  },
  "key": 75,
  "id": {
    "$oid": "61a68f4dfc13ae699b000257"
  },
  "GPS": {
    "latitude": -6.5801079,
    "longitude": -76.2609463
  },
  "city": "Shapaja",
  "name": "Providence Hospital",
  "type": "hospital",
  "address": "189 Columbus Trail",
  "department": 5
},{
  "_id": {
    "$oid": "61a690f1a7f2d302ad5606eb"
  },
  "key": 76,
  "id": {
    "$oid": "61a68f4dfc13ae699b000258"
  },
  "GPS": {
    "latitude": 57.8593919,
    "longitude": 12.4331389
  },
  "city": "Alingsås",
  "name": "Providence Seward Hospital",
  "type": "hospital",
  "address": "6130 Green Way",
  "department": 7
},{
  "_id": {
    "$oid": "61a690f1a7f2d302ad5606ec"
  },
  "key": 77,
  "id": {
    "$oid": "61a68f4dfc13ae699b000259"
  },
  "GPS": {
    "latitude": -33.93274,
    "longitude": 151.188577
  },
  "city": "Eastern Suburbs Mc",
  "name": "COVID CENTER 24",
  "type": "specialized center",
  "address": "83 Bluestem Parkway"
},{
  "_id": {
    "$oid": "61a690f1a7f2d302ad5606ed"
  },
  "key": 78,
  "id": {
    "$oid": "61a68f4dfc13ae699b00025a"
  },
  "GPS": {
    "latitude": -3.9984597,
    "longitude": 122.5129742
  },
  "city": "Kendari",
  "name": "Medical Center Barbour",
  "type": "hospital",
  "address": "866 Truax Road",
  "department": 1
},{
  "_id": {
    "$oid": "61a690f1a7f2d302ad5606ee"
  },
  "key": 79,
  "id": {
    "$oid": "61a68f4dfc13ae699b00025b"
  },
  "GPS": {
    "latitude": 8.8910633,
    "longitude": 125.0326766
  },
  "city": "Maanas",
  "name": "COVID CENTER 29",
  "type": "specialized center",
  "address": "08880 Havey Crossing"
},{
  "_id": {
    "$oid": "61a690f1a7f2d302ad5606ef"
  },
  "key": 80,
  "id": {
    "$oid": "61a68f4dfc13ae699b00025c"
  },
  "GPS": {
    "latitude": 36.650038,
    "longitude": 101.766228
  },
  "city": "Chengbei",
  "name": "COVID CENTER 27",
  "type": "specialized center",
  "address": "110 Birchwood Street"
},{
  "_id": {
    "$oid": "61a690f1a7f2d302ad5606f0"
  },
  "key": 81,
  "id": {
    "$oid": "61a68f4dfc13ae699b00025d"
  },
  "GPS": {
    "latitude": 32.790891,
    "longitude": 102.544405
  },
  "city": "Hongyuan",
  "name": "Mizell Memorial Hospital",
  "type": "hospital",
  "address": "48 Packers Crossing",
  "department": 2
},{
  "_id": {
    "$oid": "61a690f1a7f2d302ad5606f1"
  },
  "key": 82,
  "id": {
    "$oid": "61a68f4dfc13ae699b00025e"
  },
  "GPS": {
    "latitude": -0.3221142,
    "longitude": 103.1517902
  },
  "city": "Tembilahan",
  "name": "Clay County Hospital",
  "type": "hospital",
  "address": "92 Erie Circle",
  "department": 5
},{
  "_id": {
    "$oid": "61a690f1a7f2d302ad5606f2"
  },
  "key": 83,
  "id": {
    "$oid": "61a68f4dfc13ae699b00025f"
  },
  "GPS": {
    "latitude": 46.4078031,
    "longitude": 47.9992194
  },
  "city": "L’vovskiy",
  "name": "Norton Sound Regional Hospital",
  "type": "hospital",
  "address": "6 Bashford Terrace",
  "department": 3
},{
  "_id": {
    "$oid": "61a690f1a7f2d302ad5606f3"
  },
  "key": 84,
  "id": {
    "$oid": "61a68f4dfc13ae699b000260"
  },
  "GPS": {
    "latitude": 18.26196,
    "longitude": 33.90812
  },
  "city": "El Bauga",
  "name": "Community Wellness Clinic Queenstown Pharmacy",
  "type": "pharmacy",
  "address": "317 Evergreen Road"
},{
  "_id": {
    "$oid": "61a690f1a7f2d302ad5606f4"
  },
  "key": 85,
  "id": {
    "$oid": "61a68f4dfc13ae699b000261"
  },
  "GPS": {
    "latitude": 43.8564397,
    "longitude": 22.5188282
  },
  "city": "Kula",
  "name": "Providence Seward Hospital",
  "type": "hospital",
  "address": "14 Truax Center",
  "department": 3
},{
  "_id": {
    "$oid": "61a690f1a7f2d302ad5606f5"
  },
  "key": 86,
  "id": {
    "$oid": "61a68f4dfc13ae699b000262"
  },
  "GPS": {
    "latitude": 32.762127,
    "longitude": 34.97298
  },
  "city": "Tirat Karmel",
  "name": "Fairbanks Memorial Hospital",
  "type": "hospital",
  "address": "4 David Drive",
  "department": 3
},{
  "_id": {
    "$oid": "61a690f1a7f2d302ad5606f6"
  },
  "key": 87,
  "id": {
    "$oid": "61a68f4dfc13ae699b000263"
  },
  "GPS": {
    "latitude": 49.4215753,
    "longitude": 16.697784
  },
  "city": "Žďár",
  "name": "SGH OUTPATIENT PHARMACY (BLK 3)",
  "type": "pharmacy",
  "address": "7006 Glacier Hill Pass"
},{
  "_id": {
    "$oid": "61a690f1a7f2d302ad5606f7"
  },
  "key": 88,
  "id": {
    "$oid": "61a68f4dfc13ae699b000264"
  },
  "GPS": {
    "latitude": 27.4140682,
    "longitude": 64.987739
  },
  "city": "Panjgūr",
  "name": "Floyd Cherokee Medical Center",
  "type": "hospital",
  "address": "42375 Eggendart Street",
  "department": 5
},{
  "_id": {
    "$oid": "61a690f1a7f2d302ad5606f8"
  },
  "key": 89,
  "id": {
    "$oid": "61a68f4dfc13ae699b000265"
  },
  "GPS": {
    "latitude": -32.1543392,
    "longitude": -63.471433
  },
  "city": "James Craik",
  "name": "COVID CENTER 7",
  "type": "specialized center",
  "address": "1 Barnett Parkway"
},{
  "_id": {
    "$oid": "61a690f1a7f2d302ad5606f9"
  },
  "key": 90,
  "id": {
    "$oid": "61a68f4dfc13ae699b000266"
  },
  "GPS": {
    "latitude": 25.770509,
    "longitude": 113.014717
  },
  "city": "Chenzhou",
  "name": "COVID CENTER 60",
  "type": "specialized center",
  "address": "414 Schiller Crossing"
},{
  "_id": {
    "$oid": "61a690f1a7f2d302ad5606fa"
  },
  "key": 91,
  "id": {
    "$oid": "61a68f4dfc13ae699b000267"
  },
  "GPS": {
    "latitude": 26.655026,
    "longitude": 102.244683
  },
  "city": "Huili",
  "name": "Mount Elizabeth Hospital",
  "type": "pharmacy",
  "address": "84542 Northland Park"
},{
  "_id": {
    "$oid": "61a690f1a7f2d302ad5606fb"
  },
  "key": 92,
  "id": {
    "$oid": "61a68f4dfc13ae699b000268"
  },
  "GPS": {
    "latitude": 55.1286462,
    "longitude": 36.6331065
  },
  "city": "Obninsk",
  "name": "COVID CENTER 3",
  "type": "specialized center",
  "address": "7853 Iowa Lane"
},{
  "_id": {
    "$oid": "61a690f1a7f2d302ad5606fc"
  },
  "key": 93,
  "id": {
    "$oid": "61a68f4dfc13ae699b000269"
  },
  "GPS": {
    "latitude": 49.5438285,
    "longitude": 18.2789033
  },
  "city": "Kunčice pod Ondřejníkem",
  "name": "Clinic B Pharmacy",
  "type": "pharmacy",
  "address": "606 North Junction"
},{
  "_id": {
    "$oid": "61a690f1a7f2d302ad5606fd"
  },
  "key": 94,
  "id": {
    "$oid": "61a68f4dfc13ae699b00026a"
  },
  "GPS": {
    "latitude": 53.9854,
    "longitude": 30.36
  },
  "city": "Palykavichy Pyershyya",
  "name": "Nishino Pharmacy (Shaw House)",
  "type": "pharmacy",
  "address": "0190 Bunting Hill"
},{
  "_id": {
    "$oid": "61a690f1a7f2d302ad5606fe"
  },
  "key": 95,
  "id": {
    "$oid": "61a68f4dfc13ae699b00026b"
  },
  "GPS": {
    "latitude": 14.5042717,
    "longitude": 120.9923141
  },
  "city": "Buensuseso",
  "name": "COVID CENTER 32",
  "type": "specialized center",
  "address": "19 Surrey Court"
},{
  "_id": {
    "$oid": "61a690f1a7f2d302ad5606ff"
  },
  "key": 96,
  "id": {
    "$oid": "61a68f4dfc13ae699b00026c"
  },
  "GPS": {
    "latitude": 33.5727724,
    "longitude": 36.4093761
  },
  "city": "Douma",
  "name": "Petersburg Medical Center",
  "type": "hospital",
  "address": "67 Everett Center",
  "department": 4
},{
  "_id": {
    "$oid": "61a690f1a7f2d302ad560700"
  },
  "key": 97,
  "id": {
    "$oid": "61a68f4dfc13ae699b00026d"
  },
  "GPS": {
    "latitude": -9.483333,
    "longitude": -77.866667
  },
  "city": "Cochabamba",
  "name": "Specialist Compounding Pharmacy Pte Ltd",
  "type": "pharmacy",
  "address": "1722 Merry Road"
},{
  "_id": {
    "$oid": "61a690f1a7f2d302ad560701"
  },
  "key": 98,
  "id": {
    "$oid": "61a68f4dfc13ae699b00026e"
  },
  "GPS": {
    "latitude": -6.588201,
    "longitude": 106.804564
  },
  "city": "Babakan",
  "name": "Children's Hospital Of Alabama",
  "type": "hospital",
  "address": "7 Kensington Drive",
  "department": 6
},{
  "_id": {
    "$oid": "61a690f1a7f2d302ad560702"
  },
  "key": 99,
  "id": {
    "$oid": "61a68f4dfc13ae699b00026f"
  },
  "GPS": {
    "latitude": -7.4977546,
    "longitude": 108.6351043
  },
  "city": "Pasirgaru",
  "name": "Jackson Medical Center",
  "type": "hospital",
  "address": "8584 Morningstar Drive",
  "department": 8
},{
  "_id": {
    "$oid": "61a690f1a7f2d302ad560703"
  },
  "key": 100,
  "id": {
    "$oid": "61a68f4dfc13ae699b000270"
  },
  "GPS": {
    "latitude": 4.5943745,
    "longitude": -74.0740729
  },
  "city": "Candelaria",
  "name": "Southeast Alabama Medical Center",
  "type": "hospital",
  "address": "2 Green Pass",
  "department": 6
},{
  "_id": {
    "$oid": "61a690f1a7f2d302ad560704"
  },
  "key": 101,
  "id": {
    "$oid": "61a68f4dfc13ae699b000271"
  },
  "GPS": {
    "latitude": 27.353091,
    "longitude": 118.015602
  },
  "city": "Ankou",
  "name": "COVID CENTER 8",
  "type": "specialized center",
  "address": "02124 Grover Way"
},{
  "_id": {
    "$oid": "61a690f1a7f2d302ad560705"
  },
  "key": 102,
  "id": {
    "$oid": "61a68f4dfc13ae699b000272"
  },
  "GPS": {
    "latitude": 32.8676912,
    "longitude": -80.017511
  },
  "city": "Shuangxi",
  "name": "Providence Alaska Medical Center",
  "type": "hospital",
  "address": "5 Cascade Court",
  "department": 4
},{
  "_id": {
    "$oid": "61a690f1a7f2d302ad560706"
  },
  "key": 103,
  "id": {
    "$oid": "61a68f4dfc13ae699b000273"
  },
  "GPS": {
    "latitude": 40.0408242,
    "longitude": 44.5448872
  },
  "city": "Arevshat",
  "name": "Raffles Health Holland V",
  "type": "pharmacy",
  "address": "12538 Merrick Drive"
},{
  "_id": {
    "$oid": "61a690f1a7f2d302ad560707"
  },
  "key": 104,
  "id": {
    "$oid": "61a68f4dfc13ae699b000274"
  },
  "GPS": {
    "latitude": 51.5006286,
    "longitude": 19.0170774
  },
  "city": "Sędziejowice",
  "name": "University Of Alabama Hospital",
  "type": "hospital",
  "address": "395 Roxbury Road",
  "department": 1
},{
  "_id": {
    "$oid": "61a690f1a7f2d302ad560708"
  },
  "key": 105,
  "id": {
    "$oid": "61a68f4dfc13ae699b000275"
  },
  "GPS": {
    "latitude": 18.1405298,
    "longitude": 120.5168009
  },
  "city": "Paoay",
  "name": "Kanakanak Hospital",
  "type": "hospital",
  "address": "7761 Garrison Lane",
  "department": 1
},{
  "_id": {
    "$oid": "61a690f1a7f2d302ad560709"
  },
  "key": 106,
  "id": {
    "$oid": "61a68f4dfc13ae699b000276"
  },
  "GPS": {
    "latitude": 29.046809,
    "longitude": 110.482084
  },
  "city": "Tianmen",
  "name": "Andalusia Health",
  "type": "hospital",
  "address": "69 Hollow Ridge Hill",
  "department": 1
},{
  "_id": {
    "$oid": "61a690f1a7f2d302ad56070a"
  },
  "key": 107,
  "id": {
    "$oid": "61a68f4dfc13ae699b000277"
  },
  "GPS": {
    "latitude": 37.5267674,
    "longitude": 15.0586639
  },
  "city": "Catania",
  "name": "WOODS PHARMACY PTE LTD",
  "type": "pharmacy",
  "address": "1196 Fordem Parkway"
},{
  "_id": {
    "$oid": "61a690f1a7f2d302ad56070b"
  },
  "key": 108,
  "id": {
    "$oid": "61a68f4dfc13ae699b000278"
  },
  "GPS": {
    "latitude": 57.2749315,
    "longitude": 103.7420582
  },
  "city": "Rudnogorsk",
  "name": "WESTMEAD PHARMACY PTE LTD",
  "type": "pharmacy",
  "address": "672 Charing Cross Lane"
},{
  "_id": {
    "$oid": "61a690f1a7f2d302ad56070c"
  },
  "key": 109,
  "id": {
    "$oid": "61a68f4dfc13ae699b000279"
  },
  "GPS": {
    "latitude": 31.2303904,
    "longitude": 121.4737021
  },
  "city": "Shanghudi",
  "name": "Singapore General Hospital Pharmacy",
  "type": "pharmacy",
  "address": "6483 Kensington Circle"
},{
  "_id": {
    "$oid": "61a690f1a7f2d302ad56070d"
  },
  "key": 110,
  "id": {
    "$oid": "61a68f4dfc13ae699b00027a"
  },
  "GPS": {
    "latitude": 50.9575733,
    "longitude": 15.7384571
  },
  "city": "Jeżów Sudecki",
  "name": "Wrangell Medical Center",
  "type": "hospital",
  "address": "7457 4th Court",
  "department": 10
},{
  "_id": {
    "$oid": "61a690f1a7f2d302ad56070e"
  },
  "key": 111,
  "id": {
    "$oid": "61a68f4dfc13ae699b00027b"
  },
  "GPS": {
    "latitude": 36.07884,
    "longitude": 111.579554
  },
  "city": "Yaodu",
  "name": "Providence Seward Hospital",
  "type": "hospital",
  "address": "02 Kings Court",
  "department": 1
},{
  "_id": {
    "$oid": "61a690f1a7f2d302ad56070f"
  },
  "key": 112,
  "id": {
    "$oid": "61a68f4dfc13ae699b00027c"
  },
  "GPS": {
    "latitude": 26.0696179,
    "longitude": 50.5006231
  },
  "city": "Dār Kulayb",
  "name": "COVID CENTER 3",
  "type": "specialized center",
  "address": "3 Mcbride Avenue"
},{
  "_id": {
    "$oid": "61a690f1a7f2d302ad560710"
  },
  "key": 113,
  "id": {
    "$oid": "61a68f4dfc13ae699b00027d"
  },
  "GPS": {
    "latitude": 41.811979,
    "longitude": 126.918087
  },
  "city": "Linjiang",
  "name": "Rmc Jacksonville",
  "type": "hospital",
  "address": "17319 Tomscot Road",
  "department": 10
},{
  "_id": {
    "$oid": "61a690f1a7f2d302ad560711"
  },
  "key": 114,
  "id": {
    "$oid": "61a68f4dfc13ae699b00027e"
  },
  "GPS": {
    "latitude": 10.1709167,
    "longitude": -66.8915809
  },
  "city": "Cúa",
  "name": "Red Bay Hospital",
  "type": "hospital",
  "address": "703 Superior Circle",
  "department": 6
},{
  "_id": {
    "$oid": "61a690f1a7f2d302ad560712"
  },
  "key": 115,
  "id": {
    "$oid": "61a68f4dfc13ae699b00027f"
  },
  "GPS": {
    "latitude": 43.960744,
    "longitude": 124.582546
  },
  "city": "Shifo",
  "name": "COVID CENTER 17",
  "type": "specialized center",
  "address": "8 Mariners Cove Terrace"
},{
  "_id": {
    "$oid": "61a690f1a7f2d302ad560713"
  },
  "key": 116,
  "id": {
    "$oid": "61a68f4dfc13ae699b000280"
  },
  "GPS": {
    "latitude": 44.0643415,
    "longitude": 1.1011089
  },
  "city": "Castelsarrasin",
  "name": "St Joseph's Hospital",
  "type": "hospital",
  "address": "49 Reindahl Drive",
  "department": 8
},{
  "_id": {
    "$oid": "61a690f1a7f2d302ad560714"
  },
  "key": 117,
  "id": {
    "$oid": "61a68f4dfc13ae699b000281"
  },
  "GPS": {
    "latitude": 22.54817,
    "longitude": 114.131764
  },
  "city": "Luokou",
  "name": "Healing Hub @ Ang Mo Kio - Thye Hua Kwan Hospital",
  "type": "pharmacy",
  "address": "71 Ludington Center"
},{
  "_id": {
    "$oid": "61a690f1a7f2d302ad560715"
  },
  "key": 118,
  "id": {
    "$oid": "61a68f4dfc13ae699b000282"
  },
  "GPS": {
    "latitude": -12.1880654,
    "longitude": -39.734338
  },
  "city": "Ipirá",
  "name": "South Peninsula Hospital",
  "type": "hospital",
  "address": "5 Badeau Plaza",
  "department": 2
},{
  "_id": {
    "$oid": "61a690f1a7f2d302ad560716"
  },
  "key": 119,
  "id": {
    "$oid": "61a68f4dfc13ae699b000283"
  },
  "GPS": {
    "latitude": 22.521523,
    "longitude": 114.055023
  },
  "city": "Futian",
  "name": "Northeast Alabama Regional Medical Center",
  "type": "hospital",
  "address": "6849 Pearson Street",
  "department": 7
},{
  "_id": {
    "$oid": "61a690f1a7f2d302ad560717"
  },
  "key": 120,
  "id": {
    "$oid": "61a68f4dfc13ae699b000284"
  },
  "GPS": {
    "latitude": 10.2453984,
    "longitude": -74.041805
  },
  "city": "Algarrobo",
  "name": "SINGAPORE NATIONAL EYE CENTRE PTE LTD",
  "type": "pharmacy",
  "address": "496 Marcy Lane"
},{
  "_id": {
    "$oid": "61a690f1a7f2d302ad560718"
  },
  "key": 121,
  "id": {
    "$oid": "61a68f4dfc13ae699b000285"
  },
  "GPS": {
    "latitude": 31.385597,
    "longitude": 120.980736
  },
  "city": "Junshan",
  "name": "Lake Martin Community Hospital",
  "type": "hospital",
  "address": "9290 Burning Wood Park",
  "department": 8
},{
  "_id": {
    "$oid": "61a690f1a7f2d302ad560719"
  },
  "key": 122,
  "id": {
    "$oid": "61a68f4dfc13ae699b000286"
  },
  "GPS": {
    "latitude": 58.8995628,
    "longitude": 59.7081271
  },
  "city": "Is",
  "name": "Grove Hill Memorial Hospital",
  "type": "hospital",
  "address": "0 Northland Point",
  "department": 2
},{
  "_id": {
    "$oid": "61a690f1a7f2d302ad56071a"
  },
  "key": 123,
  "id": {
    "$oid": "61a68f4dfc13ae699b000287"
  },
  "GPS": {
    "latitude": 41.1283966,
    "longitude": 25.1850002
  },
  "city": "Íasmos",
  "name": "National Centre for Infectious Disease (Outpatient Pharmacy)",
  "type": "pharmacy",
  "address": "5 John Wall Plaza"
},{
  "_id": {
    "$oid": "61a690f1a7f2d302ad56071b"
  },
  "key": 124,
  "id": {
    "$oid": "61a68f4dfc13ae699b000288"
  },
  "GPS": {
    "latitude": 54.3843215,
    "longitude": 44.8151638
  },
  "city": "Novotroitsk",
  "name": "COVID CENTER 24",
  "type": "specialized center",
  "address": "8839 Myrtle Point"
},{
  "_id": {
    "$oid": "61a690f1a7f2d302ad56071c"
  },
  "key": 125,
  "id": {
    "$oid": "61a68f4dfc13ae699b000289"
  },
  "GPS": {
    "latitude": 44.8373278,
    "longitude": 18.7330664
  },
  "city": "Brka",
  "name": "University Of South Alabama Medical Center",
  "type": "hospital",
  "address": "47 Butternut Avenue",
  "department": 7
},{
  "_id": {
    "$oid": "61a690f1a7f2d302ad56071d"
  },
  "key": 126,
  "id": {
    "$oid": "61a68f4dfc13ae699b00028a"
  },
  "GPS": {
    "latitude": -8.5324245,
    "longitude": 120.7982029
  },
  "city": "Munde",
  "name": "Kingman Regional Medical Center",
  "type": "hospital",
  "address": "538 Sage Parkway",
  "department": 9
},{
  "_id": {
    "$oid": "61a690f1a7f2d302ad56071e"
  },
  "key": 127,
  "id": {
    "$oid": "61a68f4dfc13ae699b00028b"
  },
  "GPS": {
    "latitude": 6.8873531,
    "longitude": 73.113569
  },
  "city": "Dhidhdhoo",
  "name": "Pharmacy@IB CGH (The Integrated Building)",
  "type": "pharmacy",
  "address": "34992 Lakewood Gardens Hill"
},{
  "_id": {
    "$oid": "61a690f1a7f2d302ad56071f"
  },
  "key": 128,
  "id": {
    "$oid": "61a68f4dfc13ae699b00028c"
  },
  "GPS": {
    "latitude": -34.5906948,
    "longitude": -58.4794982
  },
  "city": "Del Campillo",
  "name": "Andalusia Health",
  "type": "hospital",
  "address": "01 Warrior Avenue",
  "department": 9
},{
  "_id": {
    "$oid": "61a690f1a7f2d302ad560720"
  },
  "key": 129,
  "id": {
    "$oid": "61a68f4dfc13ae699b00028d"
  },
  "GPS": {
    "latitude": 14.526832,
    "longitude": -90.1885483
  },
  "city": "Mataquescuintla",
  "name": "COVID CENTER 58",
  "type": "specialized center",
  "address": "537 Linden Plaza"
},{
  "_id": {
    "$oid": "61a690f1a7f2d302ad560721"
  },
  "key": 130,
  "id": {
    "$oid": "61a68f4dfc13ae699b00028e"
  },
  "GPS": {
    "latitude": 39.959953,
    "longitude": 116.298326
  },
  "city": "Huaidian",
  "name": "Gadsden Regional Medical Center",
  "type": "hospital",
  "address": "1 Crownhardt Court",
  "department": 10
},{
  "_id": {
    "$oid": "61a690f1a7f2d302ad560722"
  },
  "key": 131,
  "id": {
    "$oid": "61a68f4dfc13ae699b00028f"
  },
  "GPS": {
    "latitude": -11.4890016,
    "longitude": -76.6622072
  },
  "city": "San Buenaventura",
  "name": "Russell Medical Center",
  "type": "hospital",
  "address": "5 Haas Way",
  "department": 4
},{
  "_id": {
    "$oid": "61a690f1a7f2d302ad560723"
  },
  "key": 132,
  "id": {
    "$oid": "61a68f4dfc13ae699b000290"
  },
  "GPS": {
    "latitude": 28.8837687,
    "longitude": 64.3855697
  },
  "city": "Dālbandīn",
  "name": "MEDI-LINK PHARMACY",
  "type": "pharmacy",
  "address": "89 Fordem Hill"
},{
  "_id": {
    "$oid": "61a690f1a7f2d302ad560724"
  },
  "key": 133,
  "id": {
    "$oid": "61a68f4dfc13ae699b000291"
  },
  "GPS": {
    "latitude": -10.2474296,
    "longitude": 29.9104436
  },
  "city": "Luwingu",
  "name": "Dekalb Regional Medical Center",
  "type": "hospital",
  "address": "1 Coolidge Junction",
  "department": 5
},{
  "_id": {
    "$oid": "61a690f1a7f2d302ad560725"
  },
  "key": 134,
  "id": {
    "$oid": "61a68f4dfc13ae699b000292"
  },
  "GPS": {
    "latitude": 23.106401,
    "longitude": 113.459749
  },
  "city": "Huangqu",
  "name": "Alexandra Hospital Retail Pharmacy",
  "type": "pharmacy",
  "address": "195 Parkside Terrace"
},{
  "_id": {
    "$oid": "61a690f1a7f2d302ad560726"
  },
  "key": 135,
  "id": {
    "$oid": "61a68f4dfc13ae699b000293"
  },
  "GPS": {
    "latitude": -14.96617,
    "longitude": -73.3855899
  },
  "city": "Pacapausa",
  "name": "Callahan Eye Hospital",
  "type": "hospital",
  "address": "2384 Springs Place",
  "department": 6
},{
  "_id": {
    "$oid": "61a690f1a7f2d302ad560727"
  },
  "key": 136,
  "id": {
    "$oid": "61a68f4dfc13ae699b000294"
  },
  "GPS": {
    "latitude": -31.9326576,
    "longitude": -57.9020535
  },
  "city": "Quebracho",
  "name": "COVID CENTER 7",
  "type": "specialized center",
  "address": "89 Corry Lane"
},{
  "_id": {
    "$oid": "61a690f1a7f2d302ad560728"
  },
  "key": 137,
  "id": {
    "$oid": "61a68f4dfc13ae699b000295"
  },
  "GPS": {
    "latitude": 28.260189,
    "longitude": 117.069202
  },
  "city": "Yingtan",
  "name": "NATIONAL UNIVERSITY HOSPITAL (S) PTE LTD (RETAIL PHARMACY)",
  "type": "pharmacy",
  "address": "30959 Eastwood Terrace"
},{
  "_id": {
    "$oid": "61a690f1a7f2d302ad560729"
  },
  "key": 138,
  "id": {
    "$oid": "61a68f4dfc13ae699b000296"
  },
  "GPS": {
    "latitude": 35.0150933,
    "longitude": 33.7405967
  },
  "city": "Xylotymbou",
  "name": "St Vincent's St Clair",
  "type": "hospital",
  "address": "42322 Spenser Point",
  "department": 2
},{
  "_id": {
    "$oid": "61a690f1a7f2d302ad56072a"
  },
  "key": 139,
  "id": {
    "$oid": "61a68f4dfc13ae699b000297"
  },
  "GPS": {
    "latitude": 53.3791711,
    "longitude": 50.3248312
  },
  "city": "Novosemeykino",
  "name": "Northeast Alabama Regional Medical Center",
  "type": "hospital",
  "address": "78 Luster Plaza",
  "department": 7
},{
  "_id": {
    "$oid": "61a690f1a7f2d302ad56072b"
  },
  "key": 140,
  "id": {
    "$oid": "61a68f4dfc13ae699b000298"
  },
  "GPS": {
    "latitude": 36.1181827,
    "longitude": 36.5162077
  },
  "city": "Kafr Takhārīm",
  "name": "Providence Alaska Medical Center",
  "type": "hospital",
  "address": "0 Burrows Hill",
  "department": 4
},{
  "_id": {
    "$oid": "61a690f1a7f2d302ad56072c"
  },
  "key": 141,
  "id": {
    "$oid": "61a68f4dfc13ae699b000299"
  },
  "GPS": {
    "latitude": 36.6287219,
    "longitude": 140.6618666
  },
  "city": "Hitachi",
  "name": "Jurong Community Hospital Pharmacy",
  "type": "pharmacy",
  "address": "154 Mesta Parkway"
},{
  "_id": {
    "$oid": "61a690f1a7f2d302ad56072d"
  },
  "key": 142,
  "id": {
    "$oid": "61a68f4dfc13ae699b00029a"
  },
  "GPS": {
    "latitude": 23.219932,
    "longitude": 102.835223
  },
  "city": "Yuanyang",
  "name": "COVID CENTER 24",
  "type": "specialized center",
  "address": "6 Declaration Junction"
},{
  "_id": {
    "$oid": "61a690f1a7f2d302ad56072e"
  },
  "key": 143,
  "id": {
    "$oid": "61a68f4dfc13ae699b00029b"
  },
  "GPS": {
    "latitude": -37.7178812,
    "longitude": -72.2374343
  },
  "city": "Mulchén",
  "name": "Sengkang General Hospital Outpatient Pharmacy",
  "type": "pharmacy",
  "address": "2 Packers Court"
},{
  "_id": {
    "$oid": "61a690f1a7f2d302ad56072f"
  },
  "key": 144,
  "id": {
    "$oid": "61a68f4dfc13ae699b00029c"
  },
  "GPS": {
    "latitude": -3.233333,
    "longitude": 114.533333
  },
  "city": "Anjirserapat",
  "name": "CELCODE DERMAL LAB PTE LTD",
  "type": "pharmacy",
  "address": "2 Hovde Park"
},{
  "_id": {
    "$oid": "61a690f1a7f2d302ad560730"
  },
  "key": 145,
  "id": {
    "$oid": "61a68f4dfc13ae699b00029d"
  },
  "GPS": {
    "latitude": 22.948016,
    "longitude": 113.366904
  },
  "city": "Shiqiao",
  "name": "KK Emergency Pharmacy",
  "type": "pharmacy",
  "address": "2 Kinsman Park"
},{
  "_id": {
    "$oid": "61a690f1a7f2d302ad560731"
  },
  "key": 146,
  "id": {
    "$oid": "61a68f4dfc13ae699b00029e"
  },
  "GPS": {
    "latitude": 10.7179292,
    "longitude": 122.3066411
  },
  "city": "Buluangan",
  "name": "CGH Pharmacy B",
  "type": "pharmacy",
  "address": "305 Laurel Trail"
},{
  "_id": {
    "$oid": "61a690f1a7f2d302ad560732"
  },
  "key": 147,
  "id": {
    "$oid": "61a68f4dfc13ae699b00029f"
  },
  "GPS": {
    "latitude": 35.7,
    "longitude": 10.8
  },
  "city": "Banbalah",
  "name": "Citizens Baptist Medical Center",
  "type": "hospital",
  "address": "0 Iowa Place",
  "department": 5
},{
  "_id": {
    "$oid": "61a690f1a7f2d302ad560733"
  },
  "key": 148,
  "id": {
    "$oid": "61a68f4dfc13ae699b0002a0"
  },
  "GPS": {
    "latitude": 20.7365652,
    "longitude": -76.331889
  },
  "city": "Cacocum",
  "name": "Tucson Medical Center",
  "type": "hospital",
  "address": "3 Waywood Point",
  "department": 9
},{
  "_id": {
    "$oid": "61a690f1a7f2d302ad560734"
  },
  "key": 149,
  "id": {
    "$oid": "61a68f4dfc13ae699b0002a1"
  },
  "GPS": {
    "latitude": -8.2151612,
    "longitude": 112.6109257
  },
  "city": "Suwaru",
  "name": "COVID CENTER 4",
  "type": "specialized center",
  "address": "831 Oriole Center"
},{
  "_id": {
    "$oid": "61a690f1a7f2d302ad560735"
  },
  "key": 150,
  "id": {
    "$oid": "61a68f4dfc13ae699b0002a2"
  },
  "GPS": {
    "latitude": 8.6128567,
    "longitude": 81.2179434
  },
  "city": "Trincomalee",
  "name": "Jack Hughston Memorial Hospital",
  "type": "hospital",
  "address": "97 Pankratz Hill",
  "department": 5
},{
  "_id": {
    "$oid": "61a690f1a7f2d302ad560736"
  },
  "key": 151,
  "id": {
    "$oid": "61a68f4dfc13ae699b0002a3"
  },
  "GPS": {
    "latitude": 14.773124,
    "longitude": 49.3805473
  },
  "city": "Ghayl Bā Wazīr",
  "name": "COVID CENTER 26",
  "type": "specialized center",
  "address": "09 Bartillon Junction"
},{
  "_id": {
    "$oid": "61a690f1a7f2d302ad560737"
  },
  "key": 152,
  "id": {
    "$oid": "61a68f4dfc13ae699b0002a4"
  },
  "GPS": {
    "latitude": -8.4005782,
    "longitude": 113.7870822
  },
  "city": "Tempurejo",
  "name": "Crenshaw Community Hospital",
  "type": "hospital",
  "address": "10 Continental Place",
  "department": 8
},{
  "_id": {
    "$oid": "61a690f1a7f2d302ad560738"
  },
  "key": 153,
  "id": {
    "$oid": "61a68f4dfc13ae699b0002a5"
  },
  "GPS": {
    "latitude": 29.8780031,
    "longitude": 40.1043057
  },
  "city": "Sakākā",
  "name": "Haematology Pharmacy (Block 7)",
  "type": "pharmacy",
  "address": "8 2nd Terrace"
},{
  "_id": {
    "$oid": "61a690f1a7f2d302ad560739"
  },
  "key": 154,
  "id": {
    "$oid": "61a68f4dfc13ae699b0002a6"
  },
  "GPS": {
    "latitude": 39.315813,
    "longitude": 117.666466
  },
  "city": "Renfengzhuang",
  "name": "Crenshaw Community Hospital",
  "type": "hospital",
  "address": "7 Green Lane",
  "department": 4
},{
  "_id": {
    "$oid": "61a690f1a7f2d302ad56073a"
  },
  "key": 155,
  "id": {
    "$oid": "61a68f4dfc13ae699b0002a7"
  },
  "GPS": {
    "latitude": 25.757,
    "longitude": 110.12549
  },
  "city": "Li’an",
  "name": "National University Hospital (s) Pte Ltd (Pharmacy @ NCIS)",
  "type": "pharmacy",
  "address": "9836 Hoepker Court"
},{
  "_id": {
    "$oid": "61a690f1a7f2d302ad56073b"
  },
  "key": 156,
  "id": {
    "$oid": "61a68f4dfc13ae699b0002a8"
  },
  "GPS": {
    "latitude": -7.0890281,
    "longitude": 108.8610899
  },
  "city": "Pamedaran",
  "name": "Northeast Alabama Regional Medical Center",
  "type": "hospital",
  "address": "61941 Birchwood Terrace",
  "department": 4
},{
  "_id": {
    "$oid": "61a690f1a7f2d302ad56073c"
  },
  "key": 157,
  "id": {
    "$oid": "61a68f4dfc13ae699b0002a9"
  },
  "GPS": {
    "latitude": 10.4113797,
    "longitude": 107.136224
  },
  "city": "Vũng Tàu",
  "name": "Bibb Medical Center",
  "type": "hospital",
  "address": "5799 Del Sol Crossing",
  "department": 6
},{
  "_id": {
    "$oid": "61a690f1a7f2d302ad56073d"
  },
  "key": 158,
  "id": {
    "$oid": "61a68f4dfc13ae699b0002aa"
  },
  "GPS": {
    "latitude": 14.573997,
    "longitude": 121.049071
  },
  "city": "Taltal",
  "name": "Jackson Hospital & Clinic Inc",
  "type": "hospital",
  "address": "46700 Vernon Trail",
  "department": 7
},{
  "_id": {
    "$oid": "61a690f1a7f2d302ad56073e"
  },
  "key": 159,
  "id": {
    "$oid": "61a68f4dfc13ae699b0002ab"
  },
  "GPS": {
    "latitude": -25.6684553,
    "longitude": 28.5158257
  },
  "city": "Cullinan",
  "name": "St Vincent's Chilton",
  "type": "hospital",
  "address": "7 Gina Parkway",
  "department": 7
},{
  "_id": {
    "$oid": "61a690f1a7f2d302ad56073f"
  },
  "key": 160,
  "id": {
    "$oid": "61a68f4dfc13ae699b0002ac"
  },
  "GPS": {
    "latitude": 24.5167005,
    "longitude": 44.4181786
  },
  "city": "Ad Dawādimī",
  "name": "Crenshaw Community Hospital",
  "type": "hospital",
  "address": "2313 Elmside Plaza",
  "department": 3
},{
  "_id": {
    "$oid": "61a690f1a7f2d302ad560740"
  },
  "key": 161,
  "id": {
    "$oid": "61a68f4dfc13ae699b0002ad"
  },
  "GPS": {
    "latitude": 41.027474,
    "longitude": 21.335741
  },
  "city": "Bitola",
  "name": "Jack Hughston Memorial Hospital",
  "type": "hospital",
  "address": "36 Vermont Hill",
  "department": 1
},{
  "_id": {
    "$oid": "61a690f1a7f2d302ad560741"
  },
  "key": 162,
  "id": {
    "$oid": "61a68f4dfc13ae699b0002ae"
  },
  "GPS": {
    "latitude": 46.1636706,
    "longitude": 126.6828801
  },
  "city": "Xubu",
  "name": "Baptist Medical Center East",
  "type": "hospital",
  "address": "14 Burrows Hill",
  "department": 4
},{
  "_id": {
    "$oid": "61a690f1a7f2d302ad560742"
  },
  "key": 163,
  "id": {
    "$oid": "61a68f4dfc13ae699b0002af"
  },
  "GPS": {
    "latitude": -10.789321,
    "longitude": -65.3301049
  },
  "city": "Guajará Mirim",
  "name": "Jack Hughston Memorial Hospital",
  "type": "hospital",
  "address": "09585 Thackeray Court",
  "department": 8
},{
  "_id": {
    "$oid": "61a690f1a7f2d302ad560743"
  },
  "key": 164,
  "id": {
    "$oid": "61a68f4dfc13ae699b0002b0"
  },
  "GPS": {
    "latitude": 35.662808,
    "longitude": 140.164927
  },
  "city": "Yotsukaidō",
  "name": "COVID CENTER 32",
  "type": "specialized center",
  "address": "98 Paget Trail"
},{
  "_id": {
    "$oid": "61a690f1a7f2d302ad560744"
  },
  "key": 165,
  "id": {
    "$oid": "61a68f4dfc13ae699b0002b1"
  },
  "GPS": {
    "latitude": 33.997377,
    "longitude": 113.875129
  },
  "city": "Jiangguanchi",
  "name": "NATIONAL CANCER CENTRE PHARMACY (LEVEL 1)",
  "type": "pharmacy",
  "address": "2 Ryan Road"
},{
  "_id": {
    "$oid": "61a690f1a7f2d302ad560745"
  },
  "key": 166,
  "id": {
    "$oid": "61a68f4dfc13ae699b0002b2"
  },
  "GPS": {
    "latitude": -6.0329665,
    "longitude": 26.9263671
  },
  "city": "Kabalo",
  "name": "COVID CENTER 58",
  "type": "specialized center",
  "address": "5 Alpine Street"
},{
  "_id": {
    "$oid": "61a690f1a7f2d302ad560746"
  },
  "key": 167,
  "id": {
    "$oid": "61a68f4dfc13ae699b0002b3"
  },
  "GPS": {
    "latitude": 0.3987229,
    "longitude": 32.4792744
  },
  "city": "Wakiso",
  "name": "Samuel Simmonds Memorial Hospital",
  "type": "hospital",
  "address": "6631 Stephen Park",
  "department": 1
},{
  "_id": {
    "$oid": "61a690f1a7f2d302ad560747"
  },
  "key": 168,
  "id": {
    "$oid": "61a68f4dfc13ae699b0002b4"
  },
  "GPS": {
    "latitude": -54.8079502,
    "longitude": -68.3214955
  },
  "city": "Ushuaia",
  "name": "Amber Compounding Pharmacy Pte Ltd",
  "type": "pharmacy",
  "address": "5 Troy Center"
},{
  "_id": {
    "$oid": "61a690f1a7f2d302ad560748"
  },
  "key": 169,
  "id": {
    "$oid": "61a68f4dfc13ae699b0002b5"
  },
  "GPS": {
    "latitude": -24.166667,
    "longitude": 21.833333
  },
  "city": "Lokwabe",
  "name": "Community Wellness Clinic Queenstown Pharmacy",
  "type": "pharmacy",
  "address": "99 Rieder Trail"
},{
  "_id": {
    "$oid": "61a690f1a7f2d302ad560749"
  },
  "key": 170,
  "id": {
    "$oid": "61a68f4dfc13ae699b0002b6"
  },
  "GPS": {
    "latitude": 57.9788789,
    "longitude": 33.243615
  },
  "city": "Valday",
  "name": "MOHAMED MUSTAFA & SAMSUDDIN CO PTE LTD (MUSTAFA CENTRE)",
  "type": "pharmacy",
  "address": "38020 Sloan Way"
},{
  "_id": {
    "$oid": "61a690f1a7f2d302ad56074a"
  },
  "key": 171,
  "id": {
    "$oid": "61a68f4dfc13ae699b0002b7"
  },
  "GPS": {
    "latitude": 51.567832,
    "longitude": 45.8303591
  },
  "city": "Sokolovyy",
  "name": "NATIONAL HEART CENTRE PHARMACY",
  "type": "pharmacy",
  "address": "8156 Crowley Alley"
},{
  "_id": {
    "$oid": "61a690f1a7f2d302ad56074b"
  },
  "key": 172,
  "id": {
    "$oid": "61a68f4dfc13ae699b0002b8"
  },
  "GPS": {
    "latitude": 40.2252364,
    "longitude": -8.5846629
  },
  "city": "Tentúgal",
  "name": "Tucson Medical Center",
  "type": "hospital",
  "address": "36065 Atwood Parkway",
  "department": 9
},{
  "_id": {
    "$oid": "61a690f1a7f2d302ad56074c"
  },
  "key": 173,
  "id": {
    "$oid": "61a68f4dfc13ae699b0002b9"
  },
  "GPS": {
    "latitude": 0.3179939,
    "longitude": 109.4259114
  },
  "city": "Mandor",
  "name": "Pharmacy@IB CGH (The Integrated Building)",
  "type": "pharmacy",
  "address": "32 Hoard Crossing"
},{
  "_id": {
    "$oid": "61a690f1a7f2d302ad56074d"
  },
  "key": 174,
  "id": {
    "$oid": "61a68f4dfc13ae699b0002ba"
  },
  "GPS": {
    "latitude": 23.385158,
    "longitude": 113.404729
  },
  "city": "Zhongluotan",
  "name": "Medical Center Enterprise",
  "type": "hospital",
  "address": "55 Carey Alley",
  "department": 8
},{
  "_id": {
    "$oid": "61a690f1a7f2d302ad56074e"
  },
  "key": 175,
  "id": {
    "$oid": "61a68f4dfc13ae699b0002bb"
  },
  "GPS": {
    "latitude": -7.2528931,
    "longitude": 108.1886249
  },
  "city": "Kebonbencoy",
  "name": "University Of S A Children's And Women's Hos",
  "type": "hospital",
  "address": "7 Riverside Plaza",
  "department": 4
},{
  "_id": {
    "$oid": "61a690f1a7f2d302ad56074f"
  },
  "key": 176,
  "id": {
    "$oid": "61a68f4dfc13ae699b0002bc"
  },
  "GPS": {
    "latitude": 12.1941174,
    "longitude": -1.8733017
  },
  "city": "Kokologo",
  "name": "Pharmacy A Changi General Hospital",
  "type": "pharmacy",
  "address": "81 Village Point"
},{
  "_id": {
    "$oid": "61a690f1a7f2d302ad560750"
  },
  "key": 177,
  "id": {
    "$oid": "61a68f4dfc13ae699b0002bd"
  },
  "GPS": {
    "latitude": 32.5483419,
    "longitude": 120.4520149
  },
  "city": "Lianfa",
  "name": "Georgiana Medical Center",
  "type": "hospital",
  "address": "1 Cherokee Lane",
  "department": 7
},{
  "_id": {
    "$oid": "61a690f1a7f2d302ad560751"
  },
  "key": 178,
  "id": {
    "$oid": "61a68f4dfc13ae699b0002be"
  },
  "GPS": {
    "latitude": 53.83345,
    "longitude": -113.33531
  },
  "city": "Gibbons",
  "name": "Nishino Pharmacy (Shaw House)",
  "type": "pharmacy",
  "address": "855 Tony Avenue"
},{
  "_id": {
    "$oid": "61a690f1a7f2d302ad560752"
  },
  "key": 179,
  "id": {
    "$oid": "61a68f4dfc13ae699b0002bf"
  },
  "GPS": {
    "latitude": 31.34778,
    "longitude": 121.536152
  },
  "city": "Caozhen",
  "name": "University Of S A Children's And Women's Hos",
  "type": "hospital",
  "address": "48003 Vahlen Way",
  "department": 1
},{
  "_id": {
    "$oid": "61a690f1a7f2d302ad560753"
  },
  "key": 180,
  "id": {
    "$oid": "61a68f4dfc13ae699b0002c0"
  },
  "GPS": {
    "latitude": -7.2290752,
    "longitude": -35.8808337
  },
  "city": "Campina Grande",
  "name": "Lake Martin Community Hospital",
  "type": "hospital",
  "address": "8463 Oneill Lane",
  "department": 8
},{
  "_id": {
    "$oid": "61a690f1a7f2d302ad560754"
  },
  "key": 181,
  "id": {
    "$oid": "61a68f4dfc13ae699b0002c1"
  },
  "GPS": {
    "latitude": 40.67267,
    "longitude": 122.258961
  },
  "city": "Zhanqian",
  "name": "COVID CENTER 55",
  "type": "specialized center",
  "address": "4601 Anhalt Street"
},{
  "_id": {
    "$oid": "61a690f1a7f2d302ad560755"
  },
  "key": 182,
  "id": {
    "$oid": "61a68f4dfc13ae699b0002c2"
  },
  "GPS": {
    "latitude": -11.7386611,
    "longitude": -75.5611485
  },
  "city": "Marco",
  "name": "PHARMACY @ CGH MEDICAL CENTRE",
  "type": "pharmacy",
  "address": "731 Sunnyside Avenue"
},{
  "_id": {
    "$oid": "61a690f1a7f2d302ad560756"
  },
  "key": 183,
  "id": {
    "$oid": "61a68f4dfc13ae699b0002c3"
  },
  "GPS": {
    "latitude": 38.6816201,
    "longitude": -9.1534942
  },
  "city": "Almada",
  "name": "COVID CENTER 29",
  "type": "specialized center",
  "address": "25514 Bartillon Way"
},{
  "_id": {
    "$oid": "61a690f1a7f2d302ad560757"
  },
  "key": 184,
  "id": {
    "$oid": "61a68f4dfc13ae699b0002c4"
  },
  "GPS": {
    "latitude": 24.245418,
    "longitude": 112.047678
  },
  "city": "Shangshuai",
  "name": "Dekalb Regional Medical Center",
  "type": "hospital",
  "address": "29705 Red Cloud Parkway",
  "department": 4
},{
  "_id": {
    "$oid": "61a690f1a7f2d302ad560758"
  },
  "key": 185,
  "id": {
    "$oid": "61a68f4dfc13ae699b0002c5"
  },
  "GPS": {
    "latitude": -9.7085741,
    "longitude": 124.3032719
  },
  "city": "Bosen",
  "name": "Sitka Community Hospital",
  "type": "hospital",
  "address": "4190 Cottonwood Hill",
  "department": 1
},{
  "_id": {
    "$oid": "61a690f1a7f2d302ad560759"
  },
  "key": 186,
  "id": {
    "$oid": "61a68f4dfc13ae699b0002c6"
  },
  "GPS": {
    "latitude": 29.604453,
    "longitude": 112.385429
  },
  "city": "Jiuheyuan",
  "name": "COVID CENTER 35",
  "type": "specialized center",
  "address": "02301 Almo Junction"
},{
  "_id": {
    "$oid": "61a690f1a7f2d302ad56075a"
  },
  "key": 187,
  "id": {
    "$oid": "61a68f4dfc13ae699b0002c7"
  },
  "GPS": {
    "latitude": 34.0055653,
    "longitude": 133.5697428
  },
  "city": "Kawanoechō",
  "name": "Georgiana Medical Center",
  "type": "hospital",
  "address": "43 Ridgeway Way",
  "department": 2
},{
  "_id": {
    "$oid": "61a690f1a7f2d302ad56075b"
  },
  "key": 188,
  "id": {
    "$oid": "61a68f4dfc13ae699b0002c8"
  },
  "GPS": {
    "latitude": 6.3188032,
    "longitude": 16.3758145
  },
  "city": "Bozoum",
  "name": "Cordova Community Medical Center",
  "type": "hospital",
  "address": "15697 Beilfuss Hill",
  "department": 6
},{
  "_id": {
    "$oid": "61a690f1a7f2d302ad56075c"
  },
  "key": 189,
  "id": {
    "$oid": "61a68f4dfc13ae699b0002c9"
  },
  "GPS": {
    "latitude": 46.6322044,
    "longitude": -0.5664231
  },
  "city": "Parthenay",
  "name": "Haematology Pharmacy (Block 7)",
  "type": "pharmacy",
  "address": "88 Schlimgen Way"
},{
  "_id": {
    "$oid": "61a690f1a7f2d302ad56075d"
  },
  "key": 190,
  "id": {
    "$oid": "61a68f4dfc13ae699b0002ca"
  },
  "GPS": {
    "latitude": 53.9804128,
    "longitude": 27.6670286
  },
  "city": "Borovlyany",
  "name": "WATSON'S PERSONAL CARE STORES PTE LTD (WATERWAY POINT)",
  "type": "pharmacy",
  "address": "59 Steensland Road"
},{
  "_id": {
    "$oid": "61a690f1a7f2d302ad56075e"
  },
  "key": 191,
  "id": {
    "$oid": "61a68f4dfc13ae699b0002cb"
  },
  "GPS": {
    "latitude": 24.9372186,
    "longitude": 118.6422409
  },
  "city": "Huaqiao",
  "name": "Riverview Regional Medical Center",
  "type": "hospital",
  "address": "17 Mcbride Junction",
  "department": 5
},{
  "_id": {
    "$oid": "61a690f1a7f2d302ad56075f"
  },
  "key": 192,
  "id": {
    "$oid": "61a68f4dfc13ae699b0002cc"
  },
  "GPS": {
    "latitude": -22.573223,
    "longitude": -47.1731269
  },
  "city": "Artur Nogueira",
  "name": "KK Outpatient Pharmacy",
  "type": "pharmacy",
  "address": "9968 Tennyson Place"
},{
  "_id": {
    "$oid": "61a690f1a7f2d302ad560760"
  },
  "key": 193,
  "id": {
    "$oid": "61a68f4dfc13ae699b0002cd"
  },
  "GPS": {
    "latitude": 16.8802365,
    "longitude": 121.5833217
  },
  "city": "Aglipay",
  "name": "Nishino Pharmacy (Takashimaya)",
  "type": "pharmacy",
  "address": "44688 Jenifer Plaza"
},{
  "_id": {
    "$oid": "61a690f1a7f2d302ad560761"
  },
  "key": 194,
  "id": {
    "$oid": "61a68f4dfc13ae699b0002ce"
  },
  "GPS": {
    "latitude": 44.840524,
    "longitude": 82.353656
  },
  "city": "Shuanghe",
  "name": "North Baldwin Infirmary",
  "type": "hospital",
  "address": "46512 Knutson Road",
  "department": 1
},{
  "_id": {
    "$oid": "61a690f1a7f2d302ad560762"
  },
  "key": 195,
  "id": {
    "$oid": "61a68f4dfc13ae699b0002cf"
  },
  "GPS": {
    "latitude": 34.5724074,
    "longitude": 107.0351315
  },
  "city": "Shuangbaiyang",
  "name": "COVID CENTER 44",
  "type": "specialized center",
  "address": "5992 Rockefeller Avenue"
},{
  "_id": {
    "$oid": "61a690f1a7f2d302ad560763"
  },
  "key": 196,
  "id": {
    "$oid": "61a68f4dfc13ae699b0002d0"
  },
  "GPS": {
    "latitude": -3.0040574,
    "longitude": 31.9274003
  },
  "city": "Katoro",
  "name": "COVID CENTER 36",
  "type": "specialized center",
  "address": "5014 Londonderry Way"
},{
  "_id": {
    "$oid": "61a690f1a7f2d302ad560764"
  },
  "key": 197,
  "id": {
    "$oid": "61a68f4dfc13ae699b0002d1"
  },
  "GPS": {
    "latitude": 41.7977426,
    "longitude": -8.4531054
  },
  "city": "Mosteiro",
  "name": "MOUNT ELIZABETH NOVENA HOSPITAL PHARMACY",
  "type": "pharmacy",
  "address": "5 Farwell Trail"
},{
  "_id": {
    "$oid": "61a690f1a7f2d302ad560765"
  },
  "key": 198,
  "id": {
    "$oid": "61a68f4dfc13ae699b0002d2"
  },
  "GPS": {
    "latitude": 39.76624,
    "longitude": 44.8087498
  },
  "city": "Armash",
  "name": "South Peninsula Hospital",
  "type": "hospital",
  "address": "7409 Mockingbird Way",
  "department": 8
},{
  "_id": {
    "$oid": "61a690f1a7f2d302ad560766"
  },
  "key": 199,
  "id": {
    "$oid": "61a68f4dfc13ae699b0002d3"
  },
  "GPS": {
    "latitude": 10.1592286,
    "longitude": -69.0087365
  },
  "city": "Urachiche",
  "name": "CGH Pharmacy B",
  "type": "pharmacy",
  "address": "11 Dryden Crossing"
},{
  "_id": {
    "$oid": "61a690f1a7f2d302ad560767"
  },
  "key": 200,
  "id": {
    "$oid": "61a68f4efc13ae699b0002d4"
  },
  "GPS": {
    "latitude": 56.6444907,
    "longitude": 14.224297
  },
  "city": "Växjö",
  "name": "Washington County Hospital",
  "type": "hospital",
  "address": "04718 Corry Crossing",
  "department": 7
},{
  "_id": {
    "$oid": "61a690f1a7f2d302ad560768"
  },
  "key": 201,
  "id": {
    "$oid": "61a68f4efc13ae699b0002d5"
  },
  "GPS": {
    "latitude": 9.1526728,
    "longitude": 105.1960795
  },
  "city": "Cà Mau",
  "name": "COVID CENTER 22",
  "type": "specialized center",
  "address": "6 Becker Crossing"
},{
  "_id": {
    "$oid": "61a690f1a7f2d302ad560769"
  },
  "key": 202,
  "id": {
    "$oid": "61a68f4efc13ae699b0002d6"
  },
  "GPS": {
    "latitude": 31.04808,
    "longitude": 121.749495
  },
  "city": "Nanzhen",
  "name": "COVID CENTER 47",
  "type": "specialized center",
  "address": "5116 Stuart Court"
},{
  "_id": {
    "$oid": "61a690f1a7f2d302ad56076a"
  },
  "key": 203,
  "id": {
    "$oid": "61a68f4efc13ae699b0002d7"
  },
  "GPS": {
    "latitude": 34.1926332,
    "longitude": 131.9199103
  },
  "city": "Mitake",
  "name": "Crenshaw Community Hospital",
  "type": "hospital",
  "address": "56 School Court",
  "department": 4
},{
  "_id": {
    "$oid": "61a690f1a7f2d302ad56076b"
  },
  "key": 204,
  "id": {
    "$oid": "61a68f4efc13ae699b0002d8"
  },
  "GPS": {
    "latitude": -4.1828379,
    "longitude": 13.2865504
  },
  "city": "Nkayi",
  "name": "Shoals Hospital",
  "type": "hospital",
  "address": "1471 Park Meadow Hill",
  "department": 2
},{
  "_id": {
    "$oid": "61a690f1a7f2d302ad56076c"
  },
  "key": 205,
  "id": {
    "$oid": "61a68f4efc13ae699b0002d9"
  },
  "GPS": {
    "latitude": 40.3206366,
    "longitude": -8.708013
  },
  "city": "Sanguinheira",
  "name": "Baptist Medical Center East",
  "type": "hospital",
  "address": "4415 Granby Parkway",
  "department": 3
},{
  "_id": {
    "$oid": "61a690f1a7f2d302ad56076d"
  },
  "key": 206,
  "id": {
    "$oid": "61a68f4efc13ae699b0002da"
  },
  "GPS": {
    "latitude": 25.4039407,
    "longitude": 60.3732653
  },
  "city": "Konārak",
  "name": "Walker Baptist Medical Center",
  "type": "hospital",
  "address": "576 Lerdahl Road",
  "department": 2
},{
  "_id": {
    "$oid": "61a690f1a7f2d302ad56076e"
  },
  "key": 207,
  "id": {
    "$oid": "61a68f4efc13ae699b0002db"
  },
  "GPS": {
    "latitude": 47.3591366,
    "longitude": 2.8002946
  },
  "city": "Orléans",
  "name": "WELCIA-BHG LOT ONE",
  "type": "pharmacy",
  "address": "59934 Starling Alley"
},{
  "_id": {
    "$oid": "61a690f1a7f2d302ad56076f"
  },
  "key": 208,
  "id": {
    "$oid": "61a68f4efc13ae699b0002dc"
  },
  "GPS": {
    "latitude": 7.59464,
    "longitude": 6.22476
  },
  "city": "Ogaminan",
  "name": "St. Mary's Hospital",
  "type": "hospital",
  "address": "772 Kropf Lane",
  "department": 4
},{
  "_id": {
    "$oid": "61a690f1a7f2d302ad560770"
  },
  "key": 209,
  "id": {
    "$oid": "61a68f4efc13ae699b0002dd"
  },
  "GPS": {
    "latitude": 1.3573565,
    "longitude": 103.8832261
  },
  "city": "Hougang",
  "name": "Sitka Community Hospital",
  "type": "hospital",
  "address": "8 Arizona Terrace",
  "department": 3
},{
  "_id": {
    "$oid": "61a690f1a7f2d302ad560771"
  },
  "key": 210,
  "id": {
    "$oid": "61a68f4efc13ae699b0002de"
  },
  "GPS": {
    "latitude": -38.9898711,
    "longitude": 175.8087485
  },
  "city": "Turangi",
  "name": "COVID CENTER 10",
  "type": "specialized center",
  "address": "22215 Brentwood Crossing"
},{
  "_id": {
    "$oid": "61a690f1a7f2d302ad560772"
  },
  "key": 211,
  "id": {
    "$oid": "61a68f4efc13ae699b0002df"
  },
  "GPS": {
    "latitude": 57.3356106,
    "longitude": 60.1281665
  },
  "city": "Neyvo-Rudyanka",
  "name": "Brookwood Baptist Medical Center",
  "type": "hospital",
  "address": "3 Prairie Rose Way",
  "department": 9
},{
  "_id": {
    "$oid": "61a690f1a7f2d302ad560773"
  },
  "key": 212,
  "id": {
    "$oid": "61a68f4efc13ae699b0002e0"
  },
  "GPS": {
    "latitude": 0.3179939,
    "longitude": 109.4259114
  },
  "city": "Mandor",
  "name": "Callahan Eye Hospital",
  "type": "hospital",
  "address": "251 Maple Wood Road",
  "department": 8
},{
  "_id": {
    "$oid": "61a690f1a7f2d302ad560774"
  },
  "key": 213,
  "id": {
    "$oid": "61a68f4efc13ae699b0002e1"
  },
  "GPS": {
    "latitude": 49.0711781,
    "longitude": 29.8488529
  },
  "city": "Tsibulev",
  "name": "COVID CENTER 40",
  "type": "specialized center",
  "address": "19 Ridgeview Way"
},{
  "_id": {
    "$oid": "61a690f1a7f2d302ad560775"
  },
  "key": 214,
  "id": {
    "$oid": "61a68f4efc13ae699b0002e2"
  },
  "GPS": {
    "latitude": 0.4994734,
    "longitude": 101.4095405
  },
  "city": "Nangkapayung",
  "name": "COVID CENTER 51",
  "type": "specialized center",
  "address": "5 Ridgeview Crossing"
},{
  "_id": {
    "$oid": "61a690f1a7f2d302ad560776"
  },
  "key": 215,
  "id": {
    "$oid": "61a68f4efc13ae699b0002e3"
  },
  "GPS": {
    "latitude": 31.1206637,
    "longitude": 120.9061578
  },
  "city": "Wangmang",
  "name": "University Of Alabama Hospital",
  "type": "hospital",
  "address": "403 Anderson Terrace",
  "department": 6
},{
  "_id": {
    "$oid": "61a690f1a7f2d302ad560777"
  },
  "key": 216,
  "id": {
    "$oid": "61a68f4efc13ae699b0002e4"
  },
  "GPS": {
    "latitude": 39.33333,
    "longitude": 22.01667
  },
  "city": "Karpokhórion",
  "name": "Banner - University Medical Center Phoenix",
  "type": "hospital",
  "address": "7454 David Avenue",
  "department": 5
},{
  "_id": {
    "$oid": "61a690f1a7f2d302ad560778"
  },
  "key": 217,
  "id": {
    "$oid": "61a68f4efc13ae699b0002e5"
  },
  "GPS": {
    "latitude": 43.8732498,
    "longitude": -79.002342
  },
  "city": "Ajax",
  "name": "Northeast Alabama Regional Medical Center",
  "type": "hospital",
  "address": "83 Novick Crossing",
  "department": 1
},{
  "_id": {
    "$oid": "61a690f1a7f2d302ad560779"
  },
  "key": 218,
  "id": {
    "$oid": "61a68f4efc13ae699b0002e6"
  },
  "GPS": {
    "latitude": 31.181726,
    "longitude": 121.426376
  },
  "city": "Liujia",
  "name": "University Of Alabama Hospital",
  "type": "hospital",
  "address": "2 John Wall Parkway",
  "department": 5
},{
  "_id": {
    "$oid": "61a690f1a7f2d302ad56077a"
  },
  "key": 219,
  "id": {
    "$oid": "61a68f4efc13ae699b0002e7"
  },
  "GPS": {
    "latitude": 11.7775345,
    "longitude": 10.4494906
  },
  "city": "Madara",
  "name": "COVID CENTER 38",
  "type": "specialized center",
  "address": "1678 New Castle Junction"
},{
  "_id": {
    "$oid": "61a690f1a7f2d302ad56077b"
  },
  "key": 220,
  "id": {
    "$oid": "61a68f4efc13ae699b0002e8"
  },
  "GPS": {
    "latitude": 40.7608571,
    "longitude": -73.9681265
  },
  "city": "New York City",
  "name": "COVID CENTER 58",
  "type": "specialized center",
  "address": "97 Schiller Junction"
},{
  "_id": {
    "$oid": "61a690f1a7f2d302ad56077c"
  },
  "key": 221,
  "id": {
    "$oid": "61a68f4efc13ae699b0002e9"
  },
  "GPS": {
    "latitude": -6.948,
    "longitude": 113.1874
  },
  "city": "Sebegen",
  "name": "COVID CENTER 54",
  "type": "specialized center",
  "address": "459 Arapahoe Lane"
},{
  "_id": {
    "$oid": "61a690f1a7f2d302ad56077d"
  },
  "key": 222,
  "id": {
    "$oid": "61a68f4efc13ae699b0002ea"
  },
  "GPS": {
    "latitude": 44.6034915,
    "longitude": 20.45241
  },
  "city": "Barajevo",
  "name": "Pharmacy Services Centre NHG (Blk 9)",
  "type": "pharmacy",
  "address": "978 Susan Street"
},{
  "_id": {
    "$oid": "61a690f1a7f2d302ad56077e"
  },
  "key": 223,
  "id": {
    "$oid": "61a68f4efc13ae699b0002eb"
  },
  "GPS": {
    "latitude": 3.7,
    "longitude": 98.166667
  },
  "city": "Genting",
  "name": "Ketchikan Medical Center",
  "type": "hospital",
  "address": "99351 Saint Paul Parkway",
  "department": 2
},{
  "_id": {
    "$oid": "61a690f1a7f2d302ad56077f"
  },
  "key": 224,
  "id": {
    "$oid": "61a68f4efc13ae699b0002ec"
  },
  "GPS": {
    "latitude": 16.2569214,
    "longitude": 43.9436788
  },
  "city": "‘Amrān",
  "name": "Decatur Morgan Hospital-decatur Campus",
  "type": "hospital",
  "address": "765 Bartillon Terrace",
  "department": 10
},{
  "_id": {
    "$oid": "61a690f1a7f2d302ad560780"
  },
  "key": 225,
  "id": {
    "$oid": "61a68f4efc13ae699b0002ed"
  },
  "GPS": {
    "latitude": -18.2167271,
    "longitude": 28.9470422
  },
  "city": "Gokwe",
  "name": "Northwest Medical Center",
  "type": "hospital",
  "address": "14 Declaration Place",
  "department": 5
},{
  "_id": {
    "$oid": "61a690f1a7f2d302ad560781"
  },
  "key": 226,
  "id": {
    "$oid": "61a68f4efc13ae699b0002ee"
  },
  "GPS": {
    "latitude": 11.5825677,
    "longitude": 108.9912066
  },
  "city": "Phan Rang-Tháp Chàm",
  "name": "Wiregrass Medical Center",
  "type": "hospital",
  "address": "44034 Ridgeway Place",
  "department": 2
},{
  "_id": {
    "$oid": "61a690f1a7f2d302ad560782"
  },
  "key": 227,
  "id": {
    "$oid": "61a68f4efc13ae699b0002ef"
  },
  "GPS": {
    "latitude": -31.9421308,
    "longitude": -65.1916804
  },
  "city": "Basail",
  "name": "Medical Center Barbour",
  "type": "hospital",
  "address": "043 Anthes Hill",
  "department": 3
},{
  "_id": {
    "$oid": "61a690f1a7f2d302ad560783"
  },
  "key": 228,
  "id": {
    "$oid": "61a68f4efc13ae699b0002f0"
  },
  "GPS": {
    "latitude": 36.978537,
    "longitude": 117.173524
  },
  "city": "Jiyang",
  "name": "Jurong Medical Centre Pharmacy",
  "type": "pharmacy",
  "address": "821 Forest Dale Hill"
},{
  "_id": {
    "$oid": "61a690f1a7f2d302ad560784"
  },
  "key": 229,
  "id": {
    "$oid": "61a68f4efc13ae699b0002f1"
  },
  "GPS": {
    "latitude": -7.2194536,
    "longitude": 108.0045002
  },
  "city": "Cigadog Hilir",
  "name": "Canyon Vista Medical Center",
  "type": "hospital",
  "address": "048 Merry Way",
  "department": 10
},{
  "_id": {
    "$oid": "61a690f1a7f2d302ad560785"
  },
  "key": 230,
  "id": {
    "$oid": "61a68f4efc13ae699b0002f2"
  },
  "GPS": {
    "latitude": 32.540157,
    "longitude": 111.513127
  },
  "city": "Sanjiangkou",
  "name": "NHG Pharmacy (CCK Polyclinic)",
  "type": "pharmacy",
  "address": "29928 Redwing Street"
},{
  "_id": {
    "$oid": "61a690f1a7f2d302ad560786"
  },
  "key": 231,
  "id": {
    "$oid": "61a68f4efc13ae699b0002f3"
  },
  "GPS": {
    "latitude": 39.9226488,
    "longitude": -7.2372538
  },
  "city": "Idanha-a-Nova",
  "name": "COVID CENTER 9",
  "type": "specialized center",
  "address": "5413 Anthes Junction"
},{
  "_id": {
    "$oid": "61a690f1a7f2d302ad560787"
  },
  "key": 232,
  "id": {
    "$oid": "61a68f4efc13ae699b0002f4"
  },
  "GPS": {
    "latitude": 23.296786,
    "longitude": 113.823135
  },
  "city": "Xiantang",
  "name": "Wiregrass Medical Center",
  "type": "hospital",
  "address": "64 Dixon Crossing",
  "department": 6
},{
  "_id": {
    "$oid": "61a690f1a7f2d302ad560788"
  },
  "key": 233,
  "id": {
    "$oid": "61a68f4efc13ae699b0002f5"
  },
  "GPS": {
    "latitude": 36.275231,
    "longitude": 113.310158
  },
  "city": "Huangchi",
  "name": "Highlands Medical Center",
  "type": "hospital",
  "address": "9233 Carpenter Court",
  "department": 3
},{
  "_id": {
    "$oid": "61a690f1a7f2d302ad560789"
  },
  "key": 234,
  "id": {
    "$oid": "61a68f4efc13ae699b0002f6"
  },
  "GPS": {
    "latitude": -27.1009343,
    "longitude": -52.615699
  },
  "city": "Chapecó",
  "name": "Clay County Hospital",
  "type": "hospital",
  "address": "3503 Manley Street",
  "department": 1
},{
  "_id": {
    "$oid": "61a690f1a7f2d302ad56078a"
  },
  "key": 235,
  "id": {
    "$oid": "61a68f4efc13ae699b0002f7"
  },
  "GPS": {
    "latitude": 38.2070148,
    "longitude": 128.5918489
  },
  "city": "Sogcho",
  "name": "Singapore General Hospital Pharmacy",
  "type": "pharmacy",
  "address": "29008 Sunnyside Road"
},{
  "_id": {
    "$oid": "61a690f1a7f2d302ad56078b"
  },
  "key": 236,
  "id": {
    "$oid": "61a68f4efc13ae699b0002f8"
  },
  "GPS": {
    "latitude": 34.527114,
    "longitude": 108.842622
  },
  "city": "Jingyang",
  "name": "Fairbanks Memorial Hospital",
  "type": "hospital",
  "address": "1 Laurel Center",
  "department": 9
},{
  "_id": {
    "$oid": "61a690f1a7f2d302ad56078c"
  },
  "key": 237,
  "id": {
    "$oid": "61a68f4efc13ae699b0002f9"
  },
  "GPS": {
    "latitude": 49.936089,
    "longitude": 17.9738035
  },
  "city": "Velké Hoštice",
  "name": "Singapore General Hospital Pharmacy",
  "type": "pharmacy",
  "address": "94 Center Lane"
},{
  "_id": {
    "$oid": "61a690f1a7f2d302ad56078d"
  },
  "key": 238,
  "id": {
    "$oid": "61a68f4efc13ae699b0002fa"
  },
  "GPS": {
    "latitude": 9.1707145,
    "longitude": -81.8825279
  },
  "city": "Cusapín",
  "name": "NATIONAL HEART CENTRE PHARMACY",
  "type": "pharmacy",
  "address": "9 Claremont Hill"
},{
  "_id": {
    "$oid": "61a690f1a7f2d302ad56078e"
  },
  "key": 239,
  "id": {
    "$oid": "61a68f4efc13ae699b0002fb"
  },
  "GPS": {
    "latitude": -6.712398,
    "longitude": 106.8945456
  },
  "city": "Ciawi",
  "name": "COVID CENTER 29",
  "type": "specialized center",
  "address": "7099 Hermina Avenue"
},{
  "_id": {
    "$oid": "61a690f1a7f2d302ad56078f"
  },
  "key": 240,
  "id": {
    "$oid": "61a68f4efc13ae699b0002fc"
  },
  "GPS": {
    "latitude": 7.18016,
    "longitude": 124.498942
  },
  "city": "Bual",
  "name": "Jack Hughston Memorial Hospital",
  "type": "hospital",
  "address": "6477 Summerview Alley",
  "department": 1
},{
  "_id": {
    "$oid": "61a690f1a7f2d302ad560790"
  },
  "key": 241,
  "id": {
    "$oid": "61a68f4efc13ae699b0002fd"
  },
  "GPS": {
    "latitude": -29.6247579,
    "longitude": -50.8316868
  },
  "city": "Parobé",
  "name": "COVID CENTER 22",
  "type": "specialized center",
  "address": "3901 Vidon Parkway"
},{
  "_id": {
    "$oid": "61a690f1a7f2d302ad560791"
  },
  "key": 242,
  "id": {
    "$oid": "61a68f4efc13ae699b0002fe"
  },
  "GPS": {
    "latitude": 51.4700683,
    "longitude": 16.6142027
  },
  "city": "Wińsko",
  "name": "Bartlett Regional Hospital",
  "type": "hospital",
  "address": "9063 Johnson Hill",
  "department": 3
},{
  "_id": {
    "$oid": "61a690f1a7f2d302ad560792"
  },
  "key": 243,
  "id": {
    "$oid": "61a68f4efc13ae699b0002ff"
  },
  "GPS": {
    "latitude": 12.6679167,
    "longitude": 123.9881642
  },
  "city": "Curuan",
  "name": "ST ANDREW'S COMMUNITY HOSPITAL PHARMACY",
  "type": "pharmacy",
  "address": "9 Charing Cross Junction"
},{
  "_id": {
    "$oid": "61a690f1a7f2d302ad560793"
  },
  "key": 244,
  "id": {
    "$oid": "61a68f4efc13ae699b000300"
  },
  "GPS": {
    "latitude": 54.2618911,
    "longitude": 36.15775
  },
  "city": "Peremyshl’",
  "name": "Monroe County Hospital",
  "type": "hospital",
  "address": "07 Hanover Alley",
  "department": 8
},{
  "_id": {
    "$oid": "61a690f1a7f2d302ad560794"
  },
  "key": 245,
  "id": {
    "$oid": "61a68f4efc13ae699b000301"
  },
  "GPS": {
    "latitude": -33.5072907,
    "longitude": -57.7992243
  },
  "city": "Palmitas",
  "name": "Crenshaw Community Hospital",
  "type": "hospital",
  "address": "3600 Homewood Pass",
  "department": 5
},{
  "_id": {
    "$oid": "61a690f1a7f2d302ad560795"
  },
  "key": 246,
  "id": {
    "$oid": "61a68f4efc13ae699b000302"
  },
  "GPS": {
    "latitude": 19.40552,
    "longitude": -70.37985
  },
  "city": "Salsipuedes",
  "name": "Stringfellow Memorial Hospital",
  "type": "hospital",
  "address": "3 Sullivan Junction",
  "department": 9
},{
  "_id": {
    "$oid": "61a690f1a7f2d302ad560796"
  },
  "key": 247,
  "id": {
    "$oid": "61a68f4efc13ae699b000303"
  },
  "GPS": {
    "latitude": -16.0922549,
    "longitude": -72.4701945
  },
  "city": "Huancarqui",
  "name": "Prattville Baptist Hospital",
  "type": "hospital",
  "address": "869 Karstens Park",
  "department": 4
},{
  "_id": {
    "$oid": "61a690f1a7f2d302ad560797"
  },
  "key": 248,
  "id": {
    "$oid": "61a68f4efc13ae699b000304"
  },
  "GPS": {
    "latitude": -7.4157126,
    "longitude": -38.0843008
  },
  "city": "Pedra Branca",
  "name": "GLENEAGLES HOSPITAL",
  "type": "pharmacy",
  "address": "364 Beilfuss Point"
},{
  "_id": {
    "$oid": "61a690f1a7f2d302ad560798"
  },
  "key": 249,
  "id": {
    "$oid": "61a68f4efc13ae699b000305"
  },
  "GPS": {
    "latitude": 38.0375021,
    "longitude": 125.7079231
  },
  "city": "Haeju",
  "name": "D C H Regional Medical Center",
  "type": "hospital",
  "address": "9 New Castle Drive",
  "department": 9
},{
  "_id": {
    "$oid": "61a690f1a7f2d302ad560799"
  },
  "key": 250,
  "id": {
    "$oid": "61a68f4efc13ae699b000306"
  },
  "GPS": {
    "latitude": 55.889724,
    "longitude": 60.7444752
  },
  "city": "Kasli",
  "name": "Evergreen Medical Center",
  "type": "hospital",
  "address": "6 Riverside Crossing",
  "department": 6
},{
  "_id": {
    "$oid": "61a690f1a7f2d302ad56079a"
  },
  "key": 251,
  "id": {
    "$oid": "61a68f4efc13ae699b000307"
  },
  "GPS": {
    "latitude": -6.9250071,
    "longitude": 112.5036493
  },
  "city": "Canga’an",
  "name": "Ketchikan Medical Center",
  "type": "hospital",
  "address": "33161 Tomscot Trail",
  "department": 4
},{
  "_id": {
    "$oid": "61a690f1a7f2d302ad56079b"
  },
  "key": 252,
  "id": {
    "$oid": "61a68f4efc13ae699b000308"
  },
  "GPS": {
    "latitude": 8.5211284,
    "longitude": 126.121732
  },
  "city": "Barobo",
  "name": "J Paul Jones Hospital",
  "type": "hospital",
  "address": "025 Norway Maple Court",
  "department": 3
},{
  "_id": {
    "$oid": "61a690f1a7f2d302ad56079c"
  },
  "key": 253,
  "id": {
    "$oid": "61a68f4efc13ae699b000309"
  },
  "GPS": {
    "latitude": 29.1416432,
    "longitude": 119.7889248
  },
  "city": "Zhagang",
  "address": "61 Corry Way"
},{
  "_id": {
    "$oid": "61a690f1a7f2d302ad56079d"
  },
  "key": 254,
  "id": {
    "$oid": "61a68f4efc13ae699b00030a"
  },
  "GPS": {
    "latitude": -8.2637032,
    "longitude": 113.5371368
  },
  "city": "Balung",
  "name": "Fayette Medical Center",
  "type": "hospital",
  "address": "83 Kropf Center",
  "department": 1
},{
  "_id": {
    "$oid": "61a690f1a7f2d302ad56079e"
  },
  "key": 255,
  "id": {
    "$oid": "61a68f4efc13ae699b00030b"
  },
  "GPS": {
    "latitude": 7.5670301,
    "longitude": 99.745565
  },
  "city": "Na Yong",
  "name": "COVID CENTER 23",
  "type": "specialized center",
  "address": "2 Ilene Terrace"
},{
  "_id": {
    "$oid": "61a690f1a7f2d302ad56079f"
  },
  "key": 256,
  "id": {
    "$oid": "61a68f4efc13ae699b00030c"
  },
  "GPS": {
    "latitude": 39.4779651,
    "longitude": -8.0757391
  },
  "city": "Mouriscas",
  "name": "COVID CENTER 26",
  "type": "specialized center",
  "address": "1632 Riverside Lane"
},{
  "_id": {
    "$oid": "61a690f1a7f2d302ad5607a0"
  },
  "key": 257,
  "id": {
    "$oid": "61a68f4efc13ae699b00030d"
  },
  "GPS": {
    "latitude": 40.3172129,
    "longitude": -8.7543161
  },
  "city": "Tocha",
  "name": "COVID CENTER 43",
  "type": "specialized center",
  "address": "03978 Lakewood Pass"
},{
  "_id": {
    "$oid": "61a690f1a7f2d302ad5607a1"
  },
  "key": 258,
  "id": {
    "$oid": "61a68f4efc13ae699b00030e"
  },
  "GPS": {
    "latitude": -8.802,
    "longitude": 121.3118
  },
  "city": "Bhokadoke",
  "name": "Grandview Medical Center",
  "type": "hospital",
  "address": "9 Helena Terrace",
  "department": 1
},{
  "_id": {
    "$oid": "61a690f1a7f2d302ad5607a2"
  },
  "key": 259,
  "id": {
    "$oid": "61a68f4efc13ae699b00030f"
  },
  "GPS": {
    "latitude": -10.218,
    "longitude": -77.064774
  },
  "city": "Ticllos",
  "name": "COVID CENTER 28",
  "type": "specialized center",
  "address": "3 Superior Road"
},{
  "_id": {
    "$oid": "61a690f1a7f2d302ad5607a3"
  },
  "key": 260,
  "id": {
    "$oid": "61a68f4efc13ae699b000310"
  },
  "GPS": {
    "latitude": 9.7437515,
    "longitude": 1.1161166
  },
  "city": "Niamtougou",
  "name": "Bibb Medical Center",
  "type": "hospital",
  "address": "6 Stang Street",
  "department": 8
},{
  "_id": {
    "$oid": "61a690f1a7f2d302ad5607a4"
  },
  "key": 261,
  "id": {
    "$oid": "61a68f4efc13ae699b000311"
  },
  "GPS": {
    "latitude": 61.6614104,
    "longitude": 40.2019954
  },
  "city": "Nyandoma",
  "name": "Sitka Community Hospital",
  "type": "hospital",
  "address": "24 Duke Park",
  "department": 6
},{
  "_id": {
    "$oid": "61a690f1a7f2d302ad5607a5"
  },
  "key": 262,
  "id": {
    "$oid": "61a68f4efc13ae699b000312"
  },
  "GPS": {
    "latitude": 26.319938,
    "longitude": 113.810157
  },
  "city": "Shuikou",
  "name": "COVID CENTER 1",
  "type": "specialized center",
  "address": "06867 Coolidge Avenue"
},{
  "_id": {
    "$oid": "61a690f1a7f2d302ad5607a6"
  },
  "key": 263,
  "id": {
    "$oid": "61a68f4efc13ae699b000313"
  },
  "GPS": {
    "latitude": 41.6270289,
    "longitude": -8.4553604
  },
  "city": "Cruzeiro",
  "name": "COVID CENTER 46",
  "type": "specialized center",
  "address": "21 Mandrake Park"
},{
  "_id": {
    "$oid": "61a690f1a7f2d302ad5607a7"
  },
  "key": 264,
  "id": {
    "$oid": "61a68f4efc13ae699b000314"
  },
  "GPS": {
    "latitude": 35.580662,
    "longitude": 104.626282
  },
  "city": "Dongxi",
  "name": "Russellville Hospital",
  "type": "hospital",
  "address": "9 Bunker Hill Junction",
  "department": 8
},{
  "_id": {
    "$oid": "61a690f1a7f2d302ad5607a8"
  },
  "key": 265,
  "id": {
    "$oid": "61a68f4efc13ae699b000315"
  },
  "GPS": {
    "latitude": 10.2583233,
    "longitude": 123.8363399
  },
  "city": "Pangpang",
  "name": "Cordova Community Medical Center",
  "type": "hospital",
  "address": "645 Birchwood Junction",
  "department": 8
},{
  "_id": {
    "$oid": "61a690f1a7f2d302ad5607a9"
  },
  "key": 266,
  "id": {
    "$oid": "61a68f4efc13ae699b000316"
  },
  "GPS": {
    "latitude": -34.6093426,
    "longitude": -58.5069115
  },
  "city": "Gualeguaychú",
  "name": "COVID CENTER 21",
  "type": "specialized center",
  "address": "156 Golf View Park"
},{
  "_id": {
    "$oid": "61a690f1a7f2d302ad5607aa"
  },
  "key": 267,
  "id": {
    "$oid": "61a68f4efc13ae699b000317"
  },
  "GPS": {
    "latitude": 36.80752,
    "longitude": 43.03831
  },
  "city": "Sīnah",
  "name": "COVID CENTER 3",
  "type": "specialized center",
  "address": "6 Cherokee Place"
},{
  "_id": {
    "$oid": "61a690f1a7f2d302ad5607ab"
  },
  "key": 268,
  "id": {
    "$oid": "61a68f4efc13ae699b000318"
  },
  "GPS": {
    "latitude": 48.7974858,
    "longitude": 16.1084808
  },
  "city": "Vrbovec",
  "name": "Lawrence Medical Center",
  "type": "hospital",
  "address": "52939 Memorial Plaza",
  "department": 10
},{
  "_id": {
    "$oid": "61a690f1a7f2d302ad5607ac"
  },
  "key": 269,
  "id": {
    "$oid": "61a68f4efc13ae699b000319"
  },
  "GPS": {
    "latitude": 48.9237307,
    "longitude": 14.4538327
  },
  "city": "Včelná",
  "name": "St Vincent's Birmingham",
  "type": "hospital",
  "address": "8520 Sachtjen Pass",
  "department": 9
},{
  "_id": {
    "$oid": "61a690f1a7f2d302ad5607ad"
  },
  "key": 270,
  "id": {
    "$oid": "61a68f4efc13ae699b00031a"
  },
  "GPS": {
    "latitude": 31.920658,
    "longitude": 120.284938
  },
  "city": "Jiangtun",
  "name": "Samuel Simmonds Memorial Hospital",
  "type": "hospital",
  "address": "6 Green Point",
  "department": 5
}]